{"result":[{"id":10677,"media_id":"31207","title":{"english":"[Matsutou Tomoki] Naburareta Otome","japanese":"[\u677e\u4efb\u77e5\u57fa] \u306a\u3076\u3089\u308c\u305f\u4e59\u5973","pretty":"Naburareta Otome"},"images":{"pages":[{"t":"j","w":1200,"h":849},{"t":"j","w":1048,"h":1488},{"t":"j","w":1048,"h":1488},{"t":"j","w":1048,"h":1488},{"t":"j","w":1048,"h":1488},{"t":"j","w":1048,"h":1488},{"t":"j","w":1048,"h":1488},{"t":"j","w":1048,"h":1488},{"t":"j","w":1048,"h":1488},{"t":"j","w":1048,"h":1488},{"t":"j","w":1048,"h":1488},{"t":"j","w":1048,"h":1488},{"t":"j","w":1048,"h":1488},{"t":"j","w":1048,"h":1488},{"t":"j","w":1048,"h":1488},{"t":"j","w":1048,"h":1488},{"t":"j","w":1048,"h":1488},{"t":"j","w":1048,"h":1488},{"t":"j","w":1048,"h":1488},{"t":"j","w":1048,"h":1488},{"t":"j","w":1048,"h":1488},{"t":"j","w":1048,"h":1488},{"t":"j","w":1048,"h":1488},{"t":"j","w":1048,"h":1488},{"t":"j","w":1048,"h":1488},{"t":"j","w":1048,"h":1488},{"t":"j","w":1048,"h":1488},{"t":"j","w":1048,"h":1488},{"t":"j","w":1048,"h":1488},{"t":"j","w":1048,"h":1488},{"t":"j","w":1048,"h":1488},{"t":"j","w":1048,"h":1488},{"t":"j","w":1048,"h":1488},{"t":"j","w":1048,"h":1488},{"t":"j","w":1048,"h":1488},{"t":"j","w":1048,"h":1488},{"t":"j","w":1048,"h":1488},{"t":"j","w":1048,"h":1488},{"t":"j","w":1048,"h":1488},{"t":"j","w":1048,"h":1488},{"t":"j","w":1048,"h":1488},{"t":"j","w":1048,"h":1488},{"t":"j","w":1048,"h":1488},{"t":"j","w":1048,"h":1488},{"t":"j","w":1048,"h":1488},{"t":"j","w":1048,"h":1488},{"t":"j","w":1048,"h":1488},{"t":"j","w":1048,"h":1488},{"t":"j","w":1048,"h":1488},{"t":"j","w":1048,"h":1488},{"t":"j","w":1048,"h":1488},{"t":"j","w":1048,"h":1488},{"t":"j","w":1048,"h":1488},{"t":"j","w":1048,"h":1488},{"t":"j","w":1048,"h":1488},{"t":"j","w":1048,"h":1488},{"t":"j","w":1048,"h":1488},{"t":"j","w":1048,"h":1488},{"t":"j","w":1048,"h":1488},{"t":"j","w":1048,"h":1488},{"t":"j","w":1048,"h":1488},{"t":"j","w":1048,"h":1488},{"t":"j","w":1048,"h":1488},{"t":"j","w":1048,"h":1488},{"t":"j","w":1048,"h":1488},{"t":"j","w":1048,"h":1488},{"t":"j","w":1048,"h":1488},{"t":"j","w":1048,"h":1488},{"t":"j","w":1048,"h":1488},{"t":"j","w":1048,"h":1488},{"t":"j","w":1048,"h":1488},{"t":"j","w":1048,"h":1488},{"t":"j","w":1048,"h":1488},{"t":"j","w":1048,"h":1488},{"t":"j","w":1048,"h":1488},{"t":"j","w":1048,"h":1488},{"t":"j","w":1048,"h":1488},{"t":"j","w":1048,"h":1488},{"t":"j","w":1048,"h":1488},{"t":"j","w":1048,"h":1488},{"t":"j","w":1048,"h":1488},{"t":"j","w":1048,"h":1488},{"t":"j","w":1048,"h":1488},{"t":"j","w":1048,"h":1488},{"t":"j","w":1048,"h":1488},{"t":"j","w":1048,"h":1488},{"t":"j","w":1048,"h":1488},{"t":"j","w":1048,"h":1488},{"t":"j","w":1048,"h":1488},{"t":"j","w":1048,"h":1488},{"t":"j","w":1048,"h":1488},{"t":"j","w":1048,"h":1488},{"t":"j","w":1048,"h":1488},{"t":"j","w":1048,"h":1488},{"t":"j","w":1048,"h":1488},{"t":"j","w":1048,"h":1488},{"t":"j","w":1048,"h":1488},{"t":"j","w":1048,"h":1488},{"t":"j","w":1048,"h":1488},{"t":"j","w":1048,"h":1488},{"t":"j","w":1048,"h":1488},{"t":"j","w":1048,"h":1488},{"t":"j","w":1048,"h":1488},{"t":"j","w":1048,"h":1488},{"t":"j","w":1048,"h":1488},{"t":"j","w":1048,"h":1488},{"t":"j","w":1048,"h":1488},{"t":"j","w":1048,"h":1488},{"t":"j","w":1048,"h":1488},{"t":"j","w":1048,"h":1488},{"t":"j","w":1048,"h":1488},{"t":"j","w":1048,"h":1488},{"t":"j","w":1048,"h":1488},{"t":"j","w":1048,"h":1488},{"t":"j","w":1048,"h":1488},{"t":"j","w":1048,"h":1488},{"t":"j","w":1048,"h":1488},{"t":"j","w":1048,"h":1488},{"t":"j","w":1048,"h":1488},{"t":"j","w":1048,"h":1488},{"t":"j","w":1048,"h":1488},{"t":"j","w":1048,"h":1488},{"t":"j","w":1048,"h":1488},{"t":"j","w":1048,"h":1488},{"t":"j","w":1048,"h":1488},{"t":"j","w":1048,"h":1488},{"t":"j","w":1048,"h":1488},{"t":"j","w":1048,"h":1488},{"t":"j","w":1048,"h":1488},{"t":"j","w":1048,"h":1488},{"t":"j","w":1048,"h":1488},{"t":"j","w":1048,"h":1488},{"t":"j","w":1048,"h":1488},{"t":"j","w":1048,"h":1488},{"t":"j","w":1048,"h":1488},{"t":"j","w":1048,"h":1488},{"t":"j","w":1048,"h":1488},{"t":"j","w":1048,"h":1488},{"t":"j","w":1048,"h":1488},{"t":"j","w":1048,"h":1488},{"t":"j","w":1048,"h":1488},{"t":"j","w":1048,"h":1488},{"t":"j","w":1048,"h":1488},{"t":"j","w":1048,"h":1488},{"t":"j","w":1048,"h":1488},{"t":"j","w":1048,"h":1488},{"t":"j","w":1048,"h":1488},{"t":"j","w":1048,"h":1488},{"t":"j","w":1048,"h":1488},{"t":"j","w":1048,"h":1488},{"t":"j","w":1048,"h":1488},{"t":"j","w":1200,"h":849}],"cover":{"t":"j","w":350,"h":248},"thumbnail":{"t":"j","w":250,"h":177}},"scanlator":"","upload_date":1403982912,"tags":[{"id":370,"type":"tag","name":"business suit","url":"/tag/business-suit/","count":3209},{"id":779,"type":"tag","name":"futanari","url":"/tag/futanari/","count":23336},{"id":2937,"type":"tag","name":"big breasts","url":"/tag/big-breasts/","count":104551},{"id":3666,"type":"tag","name":"garter belt","url":"/tag/garter-belt/","count":7726},{"id":4435,"type":"tag","name":"gag","url":"/tag/gag/","count":7189},{"id":6900,"type":"tag","name":"miko","url":"/tag/miko/","count":2888},{"id":14007,"type":"artist","name":"matsutou tomoki","url":"/artist/matsutou-tomoki/","count":74},{"id":15658,"type":"tag","name":"bondage","url":"/tag/bondage/","count":34802},{"id":23965,"type":"tag","name":"chloroform","url":"/tag/chloroform/","count":1871},{"id":24201,"type":"tag","name":"stockings","url":"/tag/stockings/","count":65473},{"id":6346,"type":"language","name":"japanese","url":"/language/japanese/","count":193003},{"id":33173,"type":"category","name":"manga","url":"/category/manga/","count":77855},{"id":10314,"type":"tag","name":"schoolgirl uniform","url":"/tag/schoolgirl-uniform/","count":56614},{"id":23237,"type":"tag","name":"tankoubon","url":"/tag/tankoubon/","count":25192}],"num_pages":152,"num_favorites":66},{"id":88519,"media_id":"567265","title":{"english":"COMIC Penguin Club Sanzokuban 2013-03","japanese":"[\u96d1\u8a8c] \u30da\u30f3\u30ae\u30f3\u30af\u30e9\u30d6\u5c71\u8cca\u7248 2013\u5e7403\u6708\u53f7","pretty":"COMIC Penguin Club Sanzokuban 2013-03"},"images":{"pages":[{"t":"j","w":1200,"h":1710},{"t":"j","w":1200,"h":1730},{"t":"j","w":1200,"h":1708},{"t":"j","w":1200,"h":1724},{"t":"j","w":1200,"h":1702},{"t":"j","w":1200,"h":1720},{"t":"j","w":1200,"h":1704},{"t":"j","w":1200,"h":1720},{"t":"j","w":1200,"h":1697},{"t":"j","w":1200,"h":1713},{"t":"j","w":1200,"h":1721},{"t":"j","w":1200,"h":1733},{"t":"j","w":1200,"h":1720},{"t":"j","w":1279,"h":1850},{"t":"j","w":1200,"h":1716},{"t":"j","w":1200,"h":1730},{"t":"j","w":1200,"h":1716},{"t":"j","w":1280,"h":1850},{"t":"j","w":1200,"h":1720},{"t":"j","w":1200,"h":1733},{"t":"j","w":1200,"h":1720},{"t":"j","w":1277,"h":1850},{"t":"j","w":1200,"h":1726},{"t":"j","w":1277,"h":1850},{"t":"j","w":1200,"h":1729},{"t":"j","w":1272,"h":1850},{"t":"j","w":1278,"h":1850},{"t":"j","w":1269,"h":1850},{"t":"j","w":1277,"h":1850},{"t":"j","w":1267,"h":1850},{"t":"j","w":1274,"h":1850},{"t":"j","w":1266,"h":1850},{"t":"j","w":1276,"h":1850},{"t":"j","w":1267,"h":1850},{"t":"j","w":1276,"h":1850},{"t":"j","w":1268,"h":1850},{"t":"j","w":1275,"h":1850},{"t":"j","w":1266,"h":1850},{"t":"j","w":1268,"h":1850},{"t":"j","w":1263,"h":1850},{"t":"j","w":1270,"h":1850},{"t":"j","w":1260,"h":1850},{"t":"j","w":1280,"h":1850},{"t":"j","w":1269,"h":1850},{"t":"j","w":1268,"h":1850},{"t":"j","w":1260,"h":1850},{"t":"j","w":1270,"h":1850},{"t":"j","w":1259,"h":1850},{"t":"j","w":1266,"h":1850},{"t":"j","w":1256,"h":1850},{"t":"j","w":1263,"h":1850},{"t":"j","w":1255,"h":1850},{"t":"j","w":1261,"h":1850},{"t":"j","w":1253,"h":1850},{"t":"j","w":1259,"h":1850},{"t":"j","w":1251,"h":1850},{"t":"j","w":1257,"h":1850},{"t":"j","w":1249,"h":1850},{"t":"j","w":1253,"h":1850},{"t":"j","w":1245,"h":1850},{"t":"j","w":1252,"h":1850},{"t":"j","w":1245,"h":1850},{"t":"j","w":1252,"h":1850},{"t":"j","w":1245,"h":1850},{"t":"j","w":1249,"h":1850},{"t":"j","w":1243,"h":1850},{"t":"j","w":1248,"h":1850},{"t":"j","w":1239,"h":1850},{"t":"j","w":1248,"h":1850},{"t":"j","w":1241,"h":1850},{"t":"j","w":1248,"h":1850},{"t":"j","w":1240,"h":1850},{"t":"j","w":1246,"h":1850},{"t":"j","w":1238,"h":1850},{"t":"j","w":1244,"h":1850},{"t":"j","w":1236,"h":1850},{"t":"j","w":1244,"h":1850},{"t":"j","w":1234,"h":1850},{"t":"j","w":1240,"h":1850},{"t":"j","w":1233,"h":1850},{"t":"j","w":1238,"h":1850},{"t":"j","w":1230,"h":1850},{"t":"j","w":1236,"h":1850},{"t":"j","w":1227,"h":1850},{"t":"j","w":1234,"h":1850},{"t":"j","w":1225,"h":1850},{"t":"j","w":1234,"h":1850},{"t":"j","w":1225,"h":1850},{"t":"j","w":1231,"h":1850},{"t":"j","w":1222,"h":1850},{"t":"j","w":1227,"h":1850},{"t":"j","w":1221,"h":1850},{"t":"j","w":1232,"h":1850},{"t":"j","w":1223,"h":1850},{"t":"j","w":1233,"h":1850},{"t":"j","w":1222,"h":1850},{"t":"j","w":1230,"h":1850},{"t":"j","w":1218,"h":1850},{"t":"j","w":1224,"h":1850},{"t":"j","w":1216,"h":1850},{"t":"j","w":1225,"h":1850},{"t":"j","w":1215,"h":1850},{"t":"j","w":1221,"h":1850},{"t":"j","w":1212,"h":1850},{"t":"j","w":1222,"h":1850},{"t":"j","w":1212,"h":1850},{"t":"j","w":1219,"h":1850},{"t":"j","w":1210,"h":1850},{"t":"j","w":1218,"h":1850},{"t":"j","w":1207,"h":1850},{"t":"j","w":1214,"h":1850},{"t":"j","w":1205,"h":1850},{"t":"j","w":1209,"h":1850},{"t":"j","w":1203,"h":1850},{"t":"j","w":1210,"h":1850},{"t":"j","w":1205,"h":1850},{"t":"j","w":1214,"h":1850},{"t":"j","w":1205,"h":1850},{"t":"j","w":1214,"h":1850},{"t":"j","w":1205,"h":1850},{"t":"j","w":1217,"h":1850},{"t":"j","w":1208,"h":1850},{"t":"j","w":1193,"h":1850},{"t":"j","w":1204,"h":1850},{"t":"j","w":1192,"h":1850},{"t":"j","w":1204,"h":1850},{"t":"j","w":1196,"h":1850},{"t":"j","w":1205,"h":1850},{"t":"j","w":1196,"h":1850},{"t":"j","w":1207,"h":1850},{"t":"j","w":1199,"h":1850},{"t":"j","w":1209,"h":1850},{"t":"j","w":1202,"h":1850},{"t":"j","w":1210,"h":1850},{"t":"j","w":1202,"h":1850},{"t":"j","w":1213,"h":1850},{"t":"j","w":1204,"h":1850},{"t":"j","w":1214,"h":1850},{"t":"j","w":1206,"h":1850},{"t":"j","w":1217,"h":1850},{"t":"j","w":1208,"h":1850},{"t":"j","w":1218,"h":1850},{"t":"j","w":1208,"h":1850},{"t":"j","w":1221,"h":1850},{"t":"j","w":1210,"h":1850},{"t":"j","w":1221,"h":1850},{"t":"j","w":1214,"h":1850},{"t":"j","w":1224,"h":1850},{"t":"j","w":1216,"h":1850},{"t":"j","w":1226,"h":1850},{"t":"j","w":1220,"h":1850},{"t":"j","w":1229,"h":1850},{"t":"j","w":1217,"h":1850},{"t":"j","w":1225,"h":1850},{"t":"j","w":1220,"h":1850},{"t":"j","w":1231,"h":1850},{"t":"j","w":1219,"h":1850},{"t":"j","w":1230,"h":1850},{"t":"j","w":1223,"h":1850},{"t":"j","w":1233,"h":1850},{"t":"j","w":1225,"h":1850},{"t":"j","w":1234,"h":1850},{"t":"j","w":1229,"h":1850},{"t":"j","w":1237,"h":1850},{"t":"j","w":1229,"h":1850},{"t":"j","w":1238,"h":1850},{"t":"j","w":1230,"h":1850},{"t":"j","w":1241,"h":1850},{"t":"j","w":1233,"h":1850},{"t":"j","w":1242,"h":1850},{"t":"j","w":1235,"h":1850},{"t":"j","w":1244,"h":1850},{"t":"j","w":1237,"h":1850},{"t":"j","w":1245,"h":1850},{"t":"j","w":1240,"h":1850},{"t":"j","w":1247,"h":1850},{"t":"j","w":1239,"h":1850},{"t":"j","w":1245,"h":1850},{"t":"j","w":1238,"h":1850},{"t":"j","w":1249,"h":1850},{"t":"j","w":1242,"h":1850},{"t":"j","w":1250,"h":1850},{"t":"j","w":1243,"h":1850},{"t":"j","w":1249,"h":1850},{"t":"j","w":1242,"h":1850},{"t":"j","w":1247,"h":1850},{"t":"j","w":1244,"h":1850},{"t":"j","w":1256,"h":1850},{"t":"j","w":1249,"h":1850},{"t":"j","w":1258,"h":1850},{"t":"j","w":1250,"h":1850},{"t":"j","w":1259,"h":1850},{"t":"j","w":1252,"h":1850},{"t":"j","w":1260,"h":1850},{"t":"j","w":1251,"h":1850},{"t":"j","w":1263,"h":1850},{"t":"j","w":1253,"h":1850},{"t":"j","w":1264,"h":1850},{"t":"j","w":1254,"h":1850},{"t":"j","w":1265,"h":1850},{"t":"j","w":1262,"h":1850},{"t":"j","w":1277,"h":1850},{"t":"j","w":1259,"h":1850},{"t":"j","w":1269,"h":1850},{"t":"j","w":1263,"h":1850},{"t":"j","w":1270,"h":1850},{"t":"j","w":1266,"h":1850},{"t":"j","w":1275,"h":1850},{"t":"j","w":1266,"h":1850},{"t":"j","w":1277,"h":1850},{"t":"j","w":1266,"h":1850},{"t":"j","w":1276,"h":1850},{"t":"j","w":1266,"h":1850},{"t":"j","w":1273,"h":1850},{"t":"j","w":1266,"h":1850},{"t":"j","w":1277,"h":1850},{"t":"j","w":1264,"h":1850},{"t":"j","w":1277,"h":1850},{"t":"j","w":1272,"h":1850},{"t":"j","w":1200,"h":1730},{"t":"j","w":1275,"h":1850},{"t":"j","w":1200,"h":1728},{"t":"j","w":1276,"h":1850},{"t":"j","w":1200,"h":1724},{"t":"j","w":1277,"h":1850},{"t":"j","w":1200,"h":1721},{"t":"j","w":1278,"h":1850},{"t":"j","w":1200,"h":1716},{"t":"j","w":1200,"h":1733},{"t":"j","w":1200,"h":1718},{"t":"j","w":1275,"h":1850},{"t":"j","w":1200,"h":1726},{"t":"j","w":1200,"h":1732},{"t":"j","w":1200,"h":1722},{"t":"j","w":1200,"h":1733},{"t":"j","w":1200,"h":1716},{"t":"j","w":1275,"h":1850},{"t":"j","w":1200,"h":1725},{"t":"j","w":1276,"h":1850},{"t":"j","w":1200,"h":1722},{"t":"j","w":1276,"h":1850},{"t":"j","w":1200,"h":1725},{"t":"j","w":1276,"h":1850},{"t":"j","w":1200,"h":1722}],"cover":{"t":"j","w":350,"h":499},"thumbnail":{"t":"j","w":250,"h":356}},"scanlator":"","upload_date":1403998303,"tags":[{"id":370,"type":"tag","name":"business suit","url":"/tag/business-suit/","count":3209},{"id":1207,"type":"tag","name":"milf","url":"/tag/milf/","count":22887},{"id":1222,"type":"artist","name":"kaitou pink","url":"/artist/kaitou-pink/","count":53},{"id":2937,"type":"tag","name":"big breasts","url":"/tag/big-breasts/","count":103273},{"id":6661,"type":"artist","name":"ishigami kazui","url":"/artist/ishigami-kazui/","count":115},{"id":7768,"type":"artist","name":"migakeba hikaru","url":"/artist/migakeba-hikaru/","count":21},{"id":8010,"type":"tag","name":"group","url":"/tag/group/","count":72150},{"id":8378,"type":"tag","name":"glasses","url":"/tag/glasses/","count":48279},{"id":9808,"type":"artist","name":"kasuya hideo","url":"/artist/kasuya-hideo/","count":14},{"id":10436,"type":"artist","name":"kawamori misaki","url":"/artist/kawamori-misaki/","count":307},{"id":10942,"type":"artist","name":"hazuki kaoru","url":"/artist/hazuki-kaoru/","count":277},{"id":10988,"type":"tag","name":"anthology","url":"/tag/anthology/","count":10400},{"id":12859,"type":"artist","name":"hiro kazuki","url":"/artist/hiro-kazuki/","count":41},{"id":13720,"type":"tag","name":"nakadashi","url":"/tag/nakadashi/","count":42357},{"id":13989,"type":"tag","name":"ahegao","url":"/tag/ahegao/","count":29344},{"id":14112,"type":"artist","name":"tamagoro","url":"/artist/tamagoro/","count":329},{"id":14451,"type":"artist","name":"kai hiroyuki","url":"/artist/kai-hiroyuki/","count":269},{"id":18805,"type":"artist","name":"chataro","url":"/artist/chataro/","count":169},{"id":22942,"type":"tag","name":"incest","url":"/tag/incest/","count":28383},{"id":24201,"type":"tag","name":"stockings","url":"/tag/stockings/","count":64784},{"id":24380,"type":"tag","name":"pantyhose","url":"/tag/pantyhose/","count":14868},{"id":25406,"type":"artist","name":"mikemono yuu","url":"/artist/mikemono-yuu/","count":152},{"id":27935,"type":"artist","name":"nekogen","url":"/artist/nekogen/","count":487},{"id":28031,"type":"tag","name":"sister","url":"/tag/sister/","count":14555},{"id":32003,"type":"artist","name":"ohtomo takuji","url":"/artist/ohtomo-takuji/","count":295},{"id":32341,"type":"tag","name":"shotacon","url":"/tag/shotacon/","count":39737},{"id":6346,"type":"language","name":"japanese","url":"/language/japanese/","count":191613},{"id":33173,"type":"category","name":"manga","url":"/category/manga/","count":77142},{"id":10314,"type":"tag","name":"schoolgirl uniform","url":"/tag/schoolgirl-uniform/","count":56168}],"num_pages":244,"num_favorites":159},{"id":99500,"media_id":"636266","title":{"english":"GIGA69 2005-08 Vol. 8","japanese":"\u30ae\u30ac\u30ed\u30c3\u30af 2005\u5e748\u6708\u53f7 Vol.8","pretty":"GIGA69 2005-08 Vol. 8"},"images":{"pages":[{"t":"j","w":1153,"h":1524},{"t":"j","w":1070,"h":1517},{"t":"j","w":1070,"h":1516},{"t":"j","w":1060,"h":1516},{"t":"j","w":1060,"h":1516},{"t":"j","w":1066,"h":1516},{"t":"j","w":1066,"h":1517},{"t":"j","w":1070,"h":1517},{"t":"j","w":1058,"h":1517},{"t":"j","w":1058,"h":1517},{"t":"j","w":1054,"h":1517},{"t":"j","w":1060,"h":1517},{"t":"j","w":1048,"h":1517},{"t":"j","w":1066,"h":1517},{"t":"j","w":1056,"h":1517},{"t":"j","w":1068,"h":1517},{"t":"j","w":1062,"h":1517},{"t":"j","w":1054,"h":1517},{"t":"j","w":1062,"h":1517},{"t":"j","w":1064,"h":1517},{"t":"j","w":1064,"h":1517},{"t":"j","w":1040,"h":1517},{"t":"j","w":1064,"h":1517},{"t":"j","w":1034,"h":1517},{"t":"j","w":1052,"h":1517},{"t":"j","w":1060,"h":1517},{"t":"j","w":1054,"h":1517},{"t":"j","w":1044,"h":1517},{"t":"j","w":1044,"h":1517},{"t":"j","w":1058,"h":1517},{"t":"j","w":1038,"h":1517},{"t":"j","w":1046,"h":1517},{"t":"j","w":1034,"h":1517},{"t":"j","w":1036,"h":1517},{"t":"j","w":1040,"h":1517},{"t":"j","w":1034,"h":1517},{"t":"j","w":1034,"h":1517},{"t":"j","w":1036,"h":1517},{"t":"j","w":1040,"h":1517},{"t":"j","w":1054,"h":1517},{"t":"j","w":1038,"h":1517},{"t":"j","w":1038,"h":1517},{"t":"j","w":1034,"h":1517},{"t":"j","w":1050,"h":1517},{"t":"j","w":1038,"h":1517},{"t":"j","w":1036,"h":1517},{"t":"j","w":1050,"h":1517},{"t":"j","w":1036,"h":1517},{"t":"j","w":1028,"h":1517},{"t":"j","w":1032,"h":1517},{"t":"j","w":1032,"h":1517},{"t":"j","w":1034,"h":1517},{"t":"j","w":1030,"h":1517},{"t":"j","w":1028,"h":1517},{"t":"j","w":1032,"h":1517},{"t":"j","w":1036,"h":1517},{"t":"j","w":1024,"h":1517},{"t":"j","w":1038,"h":1517},{"t":"j","w":1036,"h":1517},{"t":"j","w":1036,"h":1517},{"t":"j","w":1034,"h":1517},{"t":"j","w":1036,"h":1517},{"t":"j","w":1036,"h":1517},{"t":"j","w":1032,"h":1517},{"t":"j","w":1040,"h":1517},{"t":"j","w":1042,"h":1517},{"t":"j","w":1026,"h":1517},{"t":"j","w":1028,"h":1517},{"t":"j","w":1038,"h":1517},{"t":"j","w":1018,"h":1517},{"t":"j","w":1032,"h":1517},{"t":"j","w":1020,"h":1517},{"t":"j","w":1022,"h":1517},{"t":"j","w":1034,"h":1517},{"t":"j","w":1022,"h":1517},{"t":"j","w":1022,"h":1517},{"t":"j","w":1028,"h":1517},{"t":"j","w":1022,"h":1516},{"t":"j","w":1022,"h":1517},{"t":"j","w":1020,"h":1517},{"t":"j","w":1008,"h":1517},{"t":"j","w":1018,"h":1517},{"t":"j","w":1018,"h":1517},{"t":"j","w":1030,"h":1517},{"t":"j","w":1012,"h":1517},{"t":"j","w":1030,"h":1517},{"t":"j","w":1010,"h":1517},{"t":"j","w":1018,"h":1517},{"t":"j","w":1012,"h":1517},{"t":"j","w":1026,"h":1517},{"t":"j","w":1022,"h":1517},{"t":"j","w":1020,"h":1517},{"t":"j","w":1020,"h":1517},{"t":"j","w":1014,"h":1517},{"t":"j","w":1012,"h":1517},{"t":"j","w":1014,"h":1517},{"t":"j","w":1012,"h":1517},{"t":"j","w":1014,"h":1517},{"t":"j","w":1016,"h":1517},{"t":"j","w":1006,"h":1517},{"t":"j","w":1016,"h":1517},{"t":"j","w":1020,"h":1517},{"t":"j","w":1018,"h":1517},{"t":"j","w":1010,"h":1517},{"t":"j","w":1010,"h":1517},{"t":"j","w":1010,"h":1517},{"t":"j","w":1006,"h":1517},{"t":"j","w":1010,"h":1517},{"t":"j","w":1008,"h":1517},{"t":"j","w":1014,"h":1517},{"t":"j","w":1002,"h":1517},{"t":"j","w":1004,"h":1517},{"t":"j","w":1004,"h":1517},{"t":"j","w":1006,"h":1517},{"t":"j","w":1016,"h":1517},{"t":"j","w":1008,"h":1517},{"t":"j","w":1004,"h":1517},{"t":"j","w":1000,"h":1516},{"t":"j","w":1002,"h":1517},{"t":"j","w":1075,"h":1517},{"t":"j","w":1004,"h":1517},{"t":"j","w":1004,"h":1517},{"t":"j","w":1006,"h":1517},{"t":"j","w":1000,"h":1517},{"t":"j","w":1000,"h":1517},{"t":"j","w":998,"h":1517},{"t":"j","w":1000,"h":1517},{"t":"j","w":1004,"h":1517},{"t":"j","w":1004,"h":1517},{"t":"j","w":1004,"h":1517},{"t":"j","w":1008,"h":1517},{"t":"j","w":1008,"h":1517},{"t":"j","w":1006,"h":1517},{"t":"j","w":1006,"h":1517},{"t":"j","w":1006,"h":1517},{"t":"j","w":996,"h":1517},{"t":"j","w":1000,"h":1517},{"t":"j","w":1006,"h":1517},{"t":"j","w":1008,"h":1517},{"t":"j","w":998,"h":1517},{"t":"j","w":1010,"h":1517},{"t":"j","w":1002,"h":1517},{"t":"j","w":1016,"h":1517},{"t":"j","w":1014,"h":1517},{"t":"j","w":1006,"h":1516},{"t":"j","w":1012,"h":1517},{"t":"j","w":1008,"h":1517},{"t":"j","w":1008,"h":1517},{"t":"j","w":1014,"h":1517},{"t":"j","w":1018,"h":1517},{"t":"j","w":1014,"h":1517},{"t":"j","w":1004,"h":1517},{"t":"j","w":1018,"h":1517},{"t":"j","w":1024,"h":1512},{"t":"j","w":1010,"h":1517},{"t":"j","w":1022,"h":1517},{"t":"j","w":1018,"h":1517},{"t":"j","w":1018,"h":1516},{"t":"j","w":1014,"h":1517},{"t":"j","w":1020,"h":1517},{"t":"j","w":1014,"h":1517},{"t":"j","w":1016,"h":1517},{"t":"j","w":1018,"h":1514},{"t":"j","w":1018,"h":1517},{"t":"j","w":1026,"h":1517},{"t":"j","w":1026,"h":1517},{"t":"j","w":1028,"h":1516},{"t":"j","w":1018,"h":1517},{"t":"j","w":1008,"h":1517},{"t":"j","w":1008,"h":1517},{"t":"j","w":1024,"h":1517},{"t":"j","w":1006,"h":1517},{"t":"j","w":1004,"h":1516},{"t":"j","w":1008,"h":1517},{"t":"j","w":1004,"h":1517},{"t":"j","w":1008,"h":1517},{"t":"j","w":1016,"h":1517},{"t":"j","w":1018,"h":1517},{"t":"j","w":1020,"h":1517},{"t":"j","w":1016,"h":1517},{"t":"j","w":1010,"h":1517},{"t":"j","w":1018,"h":1517},{"t":"j","w":1012,"h":1517},{"t":"j","w":1020,"h":1517},{"t":"j","w":1026,"h":1517},{"t":"j","w":1032,"h":1517},{"t":"j","w":1032,"h":1517},{"t":"j","w":1032,"h":1517},{"t":"j","w":1030,"h":1517},{"t":"j","w":1036,"h":1517},{"t":"j","w":1034,"h":1517},{"t":"j","w":1036,"h":1517},{"t":"j","w":1032,"h":1517},{"t":"j","w":1032,"h":1517},{"t":"j","w":1032,"h":1517},{"t":"j","w":1030,"h":1517},{"t":"j","w":1032,"h":1517},{"t":"j","w":1034,"h":1517},{"t":"j","w":1042,"h":1517},{"t":"j","w":1038,"h":1517},{"t":"j","w":1036,"h":1517},{"t":"j","w":1016,"h":1517},{"t":"j","w":1020,"h":1517},{"t":"j","w":1010,"h":1517},{"t":"j","w":1038,"h":1517},{"t":"j","w":1030,"h":1517},{"t":"j","w":1030,"h":1517},{"t":"j","w":1040,"h":1517},{"t":"j","w":1030,"h":1517},{"t":"j","w":1020,"h":1517},{"t":"j","w":1002,"h":1517},{"t":"j","w":1014,"h":1517},{"t":"j","w":1020,"h":1517},{"t":"j","w":1008,"h":1517},{"t":"j","w":1052,"h":1517},{"t":"j","w":1020,"h":1517},{"t":"j","w":1028,"h":1517},{"t":"j","w":1012,"h":1517},{"t":"j","w":1020,"h":1517},{"t":"j","w":1028,"h":1517},{"t":"j","w":1018,"h":1517},{"t":"j","w":1028,"h":1517},{"t":"j","w":1030,"h":1517},{"t":"j","w":1010,"h":1516},{"t":"j","w":1050,"h":1517},{"t":"j","w":1062,"h":1517},{"t":"j","w":1062,"h":1517},{"t":"j","w":1060,"h":1517},{"t":"j","w":1054,"h":1517},{"t":"j","w":1050,"h":1517},{"t":"j","w":1068,"h":1517},{"t":"j","w":1064,"h":1517},{"t":"j","w":1070,"h":1517},{"t":"j","w":1073,"h":1517},{"t":"j","w":1075,"h":1517},{"t":"j","w":1071,"h":1517}],"cover":{"t":"j","w":350,"h":463},"thumbnail":{"t":"j","w":250,"h":331}},"scanlator":"","upload_date":1404000397,"tags":[{"id":370,"type":"tag","name":"business suit","url":"/tag/business-suit/","count":3209},{"id":1586,"type":"artist","name":"okawari","url":"/artist/okawari/","count":214},{"id":2937,"type":"tag","name":"big breasts","url":"/tag/big-breasts/","count":103273},{"id":3735,"type":"tag","name":"swimsuit","url":"/tag/swimsuit/","count":19510},{"id":6105,"type":"artist","name":"nakamura mizumo","url":"/artist/nakamura-mizumo/","count":35},{"id":10988,"type":"tag","name":"anthology","url":"/tag/anthology/","count":10400},{"id":11546,"type":"artist","name":"mikuni saho","url":"/artist/mikuni-saho/","count":66},{"id":14695,"type":"artist","name":"ozaki miray","url":"/artist/ozaki-miray/","count":252},{"id":15282,"type":"artist","name":"sahara hidekazu","url":"/artist/sahara-hidekazu/","count":7},{"id":15348,"type":"tag","name":"ffm threesome","url":"/tag/ffm-threesome/","count":18197},{"id":16292,"type":"artist","name":"oonami youko","url":"/artist/oonami-youko/","count":71},{"id":17696,"type":"artist","name":"zerry fujio","url":"/artist/zerry-fujio/","count":37},{"id":26170,"type":"artist","name":"touge hiro","url":"/artist/touge-hiro/","count":77},{"id":27991,"type":"artist","name":"shinobu tanei","url":"/artist/shinobu-tanei/","count":232},{"id":6346,"type":"language","name":"japanese","url":"/language/japanese/","count":191613},{"id":33173,"type":"category","name":"manga","url":"/category/manga/","count":77142},{"id":10314,"type":"tag","name":"schoolgirl uniform","url":"/tag/schoolgirl-uniform/","count":56168},{"id":20360,"type":"artist","name":"ryuga syo","url":"/artist/ryuga-syo/","count":60},{"id":22436,"type":"artist","name":"mago","url":"/artist/mago/","count":11},{"id":25509,"type":"artist","name":"oshida j.o","url":"/artist/oshida-j-o/","count":6}],"num_pages":236,"num_favorites":22},{"id":166394,"media_id":"942144","title":{"english":"Namaiki! 2016-06","japanese":"\u30ca\u30de\u30a4\u30ad\u30c3\uff01 2016\u5e746\u6708\u53f7","pretty":"Namaiki! 2016-06"},"images":{"pages":[{"t":"j","w":1280,"h":1804},{"t":"j","w":1280,"h":1811},{"t":"j","w":1280,"h":1806},{"t":"j","w":1280,"h":1808},{"t":"j","w":1280,"h":1813},{"t":"j","w":1280,"h":1812},{"t":"j","w":1280,"h":1814},{"t":"j","w":1280,"h":1815},{"t":"j","w":1280,"h":1825},{"t":"j","w":1280,"h":1817},{"t":"j","w":1280,"h":1824},{"t":"j","w":1280,"h":1807},{"t":"j","w":1280,"h":1828},{"t":"j","w":1280,"h":1816},{"t":"j","w":1280,"h":1831},{"t":"j","w":1280,"h":1829},{"t":"j","w":1280,"h":1832},{"t":"j","w":1280,"h":1828},{"t":"j","w":1280,"h":1825},{"t":"j","w":1280,"h":1831},{"t":"j","w":1280,"h":1836},{"t":"j","w":1280,"h":1833},{"t":"j","w":1280,"h":1843},{"t":"j","w":1280,"h":1830},{"t":"j","w":1280,"h":1837},{"t":"j","w":1280,"h":1835},{"t":"j","w":1280,"h":1844},{"t":"j","w":1280,"h":1836},{"t":"j","w":1280,"h":1841},{"t":"j","w":1280,"h":1841},{"t":"j","w":1280,"h":1844},{"t":"j","w":1280,"h":1845},{"t":"j","w":1280,"h":1852},{"t":"j","w":1280,"h":1845},{"t":"j","w":1280,"h":1848},{"t":"j","w":1280,"h":1852},{"t":"j","w":1280,"h":1851},{"t":"j","w":1280,"h":1844},{"t":"j","w":1280,"h":1851},{"t":"j","w":1280,"h":1847},{"t":"j","w":1280,"h":1854},{"t":"j","w":1280,"h":1847},{"t":"j","w":1280,"h":1855},{"t":"j","w":1280,"h":1851},{"t":"j","w":1280,"h":1856},{"t":"j","w":1280,"h":1854},{"t":"j","w":1280,"h":1858},{"t":"j","w":1280,"h":1859},{"t":"j","w":1280,"h":1862},{"t":"j","w":1280,"h":1862},{"t":"j","w":1280,"h":1865},{"t":"j","w":1280,"h":1859},{"t":"j","w":1280,"h":1868},{"t":"j","w":1280,"h":1859},{"t":"j","w":1280,"h":1870},{"t":"j","w":1280,"h":1864},{"t":"j","w":1280,"h":1876},{"t":"j","w":1280,"h":1862},{"t":"j","w":1280,"h":1874},{"t":"j","w":1280,"h":1868},{"t":"j","w":1280,"h":1872},{"t":"j","w":1280,"h":1877},{"t":"j","w":1280,"h":1880},{"t":"j","w":1280,"h":1876},{"t":"j","w":1280,"h":1880},{"t":"j","w":1280,"h":1879},{"t":"j","w":1280,"h":1885},{"t":"j","w":1280,"h":1878},{"t":"j","w":1280,"h":1886},{"t":"j","w":1280,"h":1874},{"t":"j","w":1280,"h":1888},{"t":"j","w":1280,"h":1875},{"t":"j","w":1280,"h":1870},{"t":"j","w":1280,"h":1871},{"t":"j","w":1280,"h":1868},{"t":"j","w":1280,"h":1868},{"t":"j","w":1280,"h":1877},{"t":"j","w":1280,"h":1877},{"t":"j","w":1280,"h":1878},{"t":"j","w":1280,"h":1885},{"t":"j","w":1280,"h":1885},{"t":"j","w":1280,"h":1876},{"t":"j","w":1280,"h":1881},{"t":"j","w":1280,"h":1885},{"t":"j","w":1280,"h":1883},{"t":"j","w":1280,"h":1881},{"t":"j","w":1280,"h":1887},{"t":"j","w":1280,"h":1889},{"t":"j","w":1280,"h":1888},{"t":"j","w":1280,"h":1891},{"t":"j","w":1280,"h":1890},{"t":"j","w":1280,"h":1889},{"t":"j","w":1280,"h":1896},{"t":"j","w":1280,"h":1897},{"t":"j","w":1280,"h":1900},{"t":"j","w":1280,"h":1905},{"t":"j","w":1280,"h":1909},{"t":"j","w":1280,"h":1900},{"t":"j","w":1280,"h":1906},{"t":"j","w":1280,"h":1906},{"t":"j","w":1280,"h":1912},{"t":"j","w":1280,"h":1908},{"t":"j","w":1280,"h":1914},{"t":"j","w":1280,"h":1912},{"t":"j","w":1280,"h":1915},{"t":"j","w":1280,"h":1909},{"t":"j","w":1280,"h":1916},{"t":"j","w":1280,"h":1915},{"t":"j","w":1280,"h":1918},{"t":"j","w":1280,"h":1915},{"t":"j","w":1280,"h":1920},{"t":"j","w":1280,"h":1922},{"t":"j","w":1280,"h":1924},{"t":"j","w":1280,"h":1916},{"t":"j","w":1280,"h":1924},{"t":"j","w":1280,"h":1928},{"t":"j","w":1280,"h":1929},{"t":"j","w":1280,"h":1924},{"t":"j","w":1280,"h":1935},{"t":"j","w":1280,"h":1913},{"t":"j","w":1280,"h":1913},{"t":"j","w":1280,"h":1909},{"t":"j","w":1280,"h":1924},{"t":"j","w":1280,"h":1909},{"t":"j","w":1280,"h":1913},{"t":"j","w":1280,"h":1907},{"t":"j","w":1280,"h":1917},{"t":"j","w":1280,"h":1907},{"t":"j","w":1280,"h":1916},{"t":"j","w":1280,"h":1905},{"t":"j","w":1280,"h":1914},{"t":"j","w":1280,"h":1913},{"t":"j","w":1280,"h":1915},{"t":"j","w":1280,"h":1909},{"t":"j","w":1280,"h":1913},{"t":"j","w":1280,"h":1907},{"t":"j","w":1280,"h":1913},{"t":"j","w":1280,"h":1909},{"t":"j","w":1280,"h":1910},{"t":"j","w":1280,"h":1906},{"t":"j","w":1280,"h":1909},{"t":"j","w":1280,"h":1896},{"t":"j","w":1280,"h":1901},{"t":"j","w":1280,"h":1898},{"t":"j","w":1280,"h":1897},{"t":"j","w":1280,"h":1893},{"t":"j","w":1280,"h":1901},{"t":"j","w":1280,"h":1890},{"t":"j","w":1280,"h":1898},{"t":"j","w":1280,"h":1891},{"t":"j","w":1280,"h":1892},{"t":"j","w":1280,"h":1890},{"t":"j","w":1280,"h":1897},{"t":"j","w":1280,"h":1889},{"t":"j","w":1280,"h":1895},{"t":"j","w":1280,"h":1892},{"t":"j","w":1280,"h":1891},{"t":"j","w":1280,"h":1891},{"t":"j","w":1280,"h":1896},{"t":"j","w":1280,"h":1892},{"t":"j","w":1280,"h":1896},{"t":"j","w":1280,"h":1889},{"t":"j","w":1280,"h":1891},{"t":"j","w":1280,"h":1891},{"t":"j","w":1280,"h":1892},{"t":"j","w":1280,"h":1895},{"t":"j","w":1280,"h":1896},{"t":"j","w":1280,"h":1860},{"t":"j","w":1280,"h":1862},{"t":"j","w":1280,"h":1854},{"t":"j","w":1280,"h":1857},{"t":"j","w":1280,"h":1859},{"t":"j","w":1280,"h":1859},{"t":"j","w":1280,"h":1854},{"t":"j","w":1280,"h":1863},{"t":"j","w":1280,"h":1857},{"t":"j","w":1280,"h":1858},{"t":"j","w":1280,"h":1854},{"t":"j","w":1280,"h":1859},{"t":"j","w":1280,"h":1855},{"t":"j","w":1280,"h":1856},{"t":"j","w":1280,"h":1850},{"t":"j","w":1280,"h":1852},{"t":"j","w":1280,"h":1851},{"t":"j","w":1280,"h":1855},{"t":"j","w":1280,"h":1851},{"t":"j","w":1280,"h":1852},{"t":"j","w":1280,"h":1849},{"t":"j","w":1280,"h":1857},{"t":"j","w":1280,"h":1844},{"t":"j","w":1280,"h":1852},{"t":"j","w":1280,"h":1848},{"t":"j","w":1280,"h":1847},{"t":"j","w":1280,"h":1844},{"t":"j","w":1280,"h":1849},{"t":"j","w":1280,"h":1845},{"t":"j","w":1280,"h":1843},{"t":"j","w":1280,"h":1841},{"t":"j","w":1280,"h":1845},{"t":"j","w":1280,"h":1834},{"t":"j","w":1280,"h":1838},{"t":"j","w":1280,"h":1836},{"t":"j","w":1280,"h":1843},{"t":"j","w":1280,"h":1839},{"t":"j","w":1280,"h":1836},{"t":"j","w":1280,"h":1841},{"t":"j","w":1280,"h":1840},{"t":"j","w":1280,"h":1840},{"t":"j","w":1280,"h":1835},{"t":"j","w":1280,"h":1837},{"t":"j","w":1280,"h":1843},{"t":"j","w":1280,"h":1835},{"t":"j","w":1280,"h":1831},{"t":"j","w":1280,"h":1833},{"t":"j","w":1280,"h":1836},{"t":"j","w":1280,"h":1832},{"t":"j","w":1280,"h":1841},{"t":"j","w":1280,"h":1832},{"t":"j","w":1280,"h":1835},{"t":"j","w":1280,"h":1828},{"t":"j","w":1280,"h":1835},{"t":"j","w":1280,"h":1833},{"t":"j","w":1280,"h":1835},{"t":"j","w":1280,"h":1825},{"t":"j","w":1280,"h":1824},{"t":"j","w":1280,"h":1828},{"t":"j","w":1280,"h":1830},{"t":"j","w":1280,"h":1819},{"t":"j","w":1280,"h":1828},{"t":"j","w":1280,"h":1824},{"t":"j","w":1280,"h":1830},{"t":"j","w":1280,"h":1809},{"t":"j","w":1280,"h":1808},{"t":"j","w":1280,"h":1804},{"t":"j","w":1280,"h":1815},{"t":"j","w":1280,"h":1805},{"t":"j","w":1280,"h":1805},{"t":"j","w":1280,"h":1811}],"cover":{"t":"j","w":350,"h":493},"thumbnail":{"t":"j","w":250,"h":352}},"scanlator":"","upload_date":1465776403,"tags":[{"id":370,"type":"tag","name":"business suit","url":"/tag/business-suit/","count":3209},{"id":8378,"type":"tag","name":"glasses","url":"/tag/glasses/","count":48712},{"id":10988,"type":"tag","name":"anthology","url":"/tag/anthology/","count":10400},{"id":2937,"type":"tag","name":"big breasts","url":"/tag/big-breasts/","count":104551},{"id":10693,"type":"tag","name":"dougi","url":"/tag/dougi/","count":704},{"id":1207,"type":"tag","name":"milf","url":"/tag/milf/","count":22887},{"id":24380,"type":"tag","name":"pantyhose","url":"/tag/pantyhose/","count":14868},{"id":2669,"type":"artist","name":"abe tsukumo","url":"/artist/abe-tsukumo/","count":70},{"id":18812,"type":"artist","name":"adachi takumi","url":"/artist/adachi-takumi/","count":75},{"id":26788,"type":"artist","name":"core-suke","url":"/artist/core-suke/","count":50},{"id":28418,"type":"artist","name":"ichiko","url":"/artist/ichiko/","count":224},{"id":20522,"type":"artist","name":"kakei hidetaka","url":"/artist/kakei-hidetaka/","count":43},{"id":22456,"type":"artist","name":"manabe jouji","url":"/artist/manabe-jouji/","count":413},{"id":23450,"type":"artist","name":"takeshita kenjirou","url":"/artist/takeshita-kenjirou/","count":41},{"id":27110,"type":"artist","name":"zen9","url":"/artist/zen9/","count":263},{"id":33173,"type":"category","name":"manga","url":"/category/manga/","count":77855},{"id":6346,"type":"language","name":"japanese","url":"/language/japanese/","count":193003},{"id":52610,"type":"artist","name":"xiaowoo","url":"/artist/xiaowoo/","count":36}],"num_pages":238,"num_favorites":204},{"id":207153,"media_id":"1110190","title":{"english":"Monthly Vitaman 2017-09 [Digital]","japanese":"\u6708\u520a \u30d3\u30bf\u30de\u30f3 2017\u5e749\u6708\u53f7 [DL\u7248]","pretty":"Monthly Vitaman 2017-09"},"images":{"pages":[{"t":"j","w":655,"h":928},{"t":"j","w":655,"h":928},{"t":"j","w":655,"h":928},{"t":"j","w":655,"h":928},{"t":"j","w":655,"h":928},{"t":"j","w":655,"h":928},{"t":"j","w":655,"h":928},{"t":"j","w":655,"h":928},{"t":"j","w":655,"h":928},{"t":"j","w":655,"h":928},{"t":"j","w":655,"h":928},{"t":"j","w":655,"h":928},{"t":"j","w":655,"h":928},{"t":"j","w":655,"h":928},{"t":"j","w":655,"h":928},{"t":"j","w":655,"h":928},{"t":"j","w":655,"h":928},{"t":"j","w":655,"h":928},{"t":"j","w":655,"h":928},{"t":"j","w":655,"h":928},{"t":"j","w":655,"h":928},{"t":"j","w":655,"h":928},{"t":"j","w":655,"h":928},{"t":"j","w":655,"h":928},{"t":"j","w":655,"h":928},{"t":"j","w":655,"h":928},{"t":"j","w":655,"h":928},{"t":"j","w":655,"h":928},{"t":"j","w":655,"h":928},{"t":"j","w":655,"h":928},{"t":"j","w":655,"h":928},{"t":"j","w":655,"h":928},{"t":"j","w":655,"h":928},{"t":"j","w":655,"h":928},{"t":"j","w":655,"h":928},{"t":"j","w":655,"h":928},{"t":"j","w":655,"h":928},{"t":"j","w":655,"h":928},{"t":"j","w":655,"h":928},{"t":"j","w":655,"h":928},{"t":"j","w":655,"h":928},{"t":"j","w":655,"h":928},{"t":"j","w":655,"h":928},{"t":"j","w":655,"h":928},{"t":"j","w":655,"h":928},{"t":"j","w":655,"h":928},{"t":"j","w":655,"h":928},{"t":"j","w":655,"h":928},{"t":"j","w":655,"h":928},{"t":"j","w":655,"h":928},{"t":"j","w":655,"h":928},{"t":"j","w":655,"h":928},{"t":"j","w":655,"h":928},{"t":"j","w":655,"h":928},{"t":"j","w":655,"h":928},{"t":"j","w":655,"h":928},{"t":"j","w":655,"h":928},{"t":"j","w":655,"h":928},{"t":"j","w":655,"h":928},{"t":"j","w":655,"h":928},{"t":"j","w":655,"h":928},{"t":"j","w":655,"h":928},{"t":"j","w":655,"h":928},{"t":"j","w":655,"h":928},{"t":"j","w":655,"h":928},{"t":"j","w":655,"h":928},{"t":"j","w":655,"h":928},{"t":"j","w":655,"h":928},{"t":"j","w":655,"h":928},{"t":"j","w":655,"h":928},{"t":"j","w":655,"h":928},{"t":"j","w":655,"h":928},{"t":"j","w":655,"h":928},{"t":"j","w":655,"h":928},{"t":"j","w":655,"h":928},{"t":"j","w":655,"h":928},{"t":"j","w":655,"h":928},{"t":"j","w":655,"h":928},{"t":"j","w":655,"h":928},{"t":"j","w":655,"h":928},{"t":"j","w":655,"h":928},{"t":"j","w":655,"h":928},{"t":"j","w":655,"h":928},{"t":"j","w":655,"h":928},{"t":"j","w":655,"h":928},{"t":"j","w":655,"h":928},{"t":"j","w":655,"h":928},{"t":"j","w":655,"h":928},{"t":"j","w":655,"h":928},{"t":"j","w":655,"h":928},{"t":"j","w":655,"h":928},{"t":"j","w":655,"h":928},{"t":"j","w":655,"h":928},{"t":"j","w":655,"h":928},{"t":"j","w":655,"h":928},{"t":"j","w":655,"h":928},{"t":"j","w":655,"h":928},{"t":"j","w":655,"h":928},{"t":"j","w":655,"h":928},{"t":"j","w":655,"h":928},{"t":"j","w":655,"h":928},{"t":"j","w":655,"h":928},{"t":"j","w":655,"h":928},{"t":"j","w":655,"h":928},{"t":"j","w":655,"h":928},{"t":"j","w":655,"h":928},{"t":"j","w":655,"h":928},{"t":"j","w":655,"h":928},{"t":"j","w":655,"h":928},{"t":"j","w":655,"h":928},{"t":"j","w":655,"h":928},{"t":"j","w":655,"h":928},{"t":"j","w":655,"h":928},{"t":"j","w":655,"h":928},{"t":"j","w":655,"h":928},{"t":"j","w":655,"h":928},{"t":"j","w":655,"h":928},{"t":"j","w":655,"h":928},{"t":"j","w":655,"h":928},{"t":"j","w":655,"h":928},{"t":"j","w":655,"h":928},{"t":"j","w":655,"h":928},{"t":"j","w":655,"h":928},{"t":"j","w":655,"h":928},{"t":"j","w":655,"h":928},{"t":"j","w":655,"h":928},{"t":"j","w":655,"h":928},{"t":"j","w":655,"h":928},{"t":"j","w":655,"h":928},{"t":"j","w":655,"h":928},{"t":"j","w":655,"h":928},{"t":"j","w":655,"h":928},{"t":"j","w":655,"h":928},{"t":"j","w":655,"h":928},{"t":"j","w":655,"h":928},{"t":"j","w":655,"h":928},{"t":"j","w":655,"h":928},{"t":"j","w":655,"h":928},{"t":"j","w":655,"h":928},{"t":"j","w":655,"h":928},{"t":"j","w":655,"h":928},{"t":"j","w":655,"h":928},{"t":"j","w":655,"h":928},{"t":"j","w":655,"h":928},{"t":"j","w":655,"h":928},{"t":"j","w":655,"h":928},{"t":"j","w":655,"h":928},{"t":"j","w":655,"h":928},{"t":"j","w":655,"h":928},{"t":"j","w":655,"h":928},{"t":"j","w":655,"h":928},{"t":"j","w":655,"h":928},{"t":"j","w":655,"h":928},{"t":"j","w":655,"h":928},{"t":"j","w":655,"h":928},{"t":"j","w":655,"h":928},{"t":"j","w":655,"h":928},{"t":"j","w":655,"h":928},{"t":"j","w":655,"h":928},{"t":"j","w":655,"h":928},{"t":"j","w":655,"h":928},{"t":"j","w":655,"h":928},{"t":"j","w":655,"h":928},{"t":"j","w":655,"h":928},{"t":"j","w":655,"h":928},{"t":"j","w":655,"h":928},{"t":"j","w":655,"h":928},{"t":"j","w":655,"h":928},{"t":"j","w":655,"h":928},{"t":"j","w":655,"h":928},{"t":"j","w":655,"h":928},{"t":"j","w":655,"h":928},{"t":"j","w":655,"h":928},{"t":"j","w":655,"h":928},{"t":"j","w":655,"h":928},{"t":"j","w":655,"h":928},{"t":"j","w":655,"h":928},{"t":"j","w":655,"h":928},{"t":"j","w":655,"h":928},{"t":"j","w":655,"h":928},{"t":"j","w":655,"h":928},{"t":"j","w":655,"h":928},{"t":"j","w":655,"h":928},{"t":"j","w":655,"h":928},{"t":"j","w":655,"h":928},{"t":"j","w":655,"h":928},{"t":"j","w":655,"h":928},{"t":"j","w":655,"h":928},{"t":"j","w":655,"h":928},{"t":"j","w":655,"h":928},{"t":"j","w":655,"h":928},{"t":"j","w":655,"h":928},{"t":"j","w":655,"h":928},{"t":"j","w":655,"h":928},{"t":"j","w":655,"h":928},{"t":"j","w":655,"h":928},{"t":"j","w":655,"h":928},{"t":"j","w":655,"h":928},{"t":"j","w":655,"h":928},{"t":"j","w":655,"h":928},{"t":"j","w":655,"h":928},{"t":"j","w":655,"h":928},{"t":"j","w":655,"h":928},{"t":"j","w":655,"h":928},{"t":"j","w":655,"h":928},{"t":"j","w":655,"h":928},{"t":"j","w":655,"h":928},{"t":"j","w":655,"h":928},{"t":"j","w":655,"h":928},{"t":"j","w":655,"h":928},{"t":"j","w":655,"h":928},{"t":"j","w":655,"h":928},{"t":"j","w":655,"h":928},{"t":"j","w":655,"h":928},{"t":"j","w":655,"h":928},{"t":"j","w":655,"h":928},{"t":"j","w":655,"h":928},{"t":"j","w":655,"h":928},{"t":"j","w":655,"h":928},{"t":"j","w":655,"h":928},{"t":"j","w":655,"h":928},{"t":"j","w":655,"h":928},{"t":"j","w":655,"h":928},{"t":"j","w":655,"h":928},{"t":"j","w":655,"h":928},{"t":"j","w":655,"h":928},{"t":"j","w":655,"h":928},{"t":"j","w":655,"h":928},{"t":"j","w":655,"h":928},{"t":"j","w":655,"h":928},{"t":"j","w":655,"h":928},{"t":"j","w":655,"h":928},{"t":"j","w":655,"h":928},{"t":"j","w":655,"h":928},{"t":"j","w":655,"h":928},{"t":"j","w":655,"h":928},{"t":"j","w":655,"h":928},{"t":"j","w":655,"h":928},{"t":"j","w":655,"h":928},{"t":"j","w":655,"h":928},{"t":"j","w":655,"h":928},{"t":"j","w":655,"h":928},{"t":"j","w":655,"h":928},{"t":"j","w":655,"h":928},{"t":"j","w":655,"h":928},{"t":"j","w":655,"h":928},{"t":"j","w":655,"h":928},{"t":"j","w":655,"h":928},{"t":"j","w":655,"h":928},{"t":"j","w":655,"h":928},{"t":"j","w":655,"h":928},{"t":"j","w":655,"h":928},{"t":"j","w":655,"h":928}],"cover":{"t":"j","w":350,"h":496},"thumbnail":{"t":"j","w":250,"h":354}},"scanlator":"","upload_date":1504590814,"tags":[{"id":370,"type":"tag","name":"business suit","url":"/tag/business-suit/","count":3209},{"id":10988,"type":"tag","name":"anthology","url":"/tag/anthology/","count":10400},{"id":8368,"type":"tag","name":"full censorship","url":"/tag/full-censorship/","count":17000},{"id":2937,"type":"tag","name":"big breasts","url":"/tag/big-breasts/","count":103273},{"id":1207,"type":"tag","name":"milf","url":"/tag/milf/","count":22588},{"id":8141,"type":"artist","name":"asamori mizuki","url":"/artist/asamori-mizuki/","count":56},{"id":30292,"type":"artist","name":"azuma taira","url":"/artist/azuma-taira/","count":113},{"id":1596,"type":"artist","name":"higashino mikan","url":"/artist/higashino-mikan/","count":78},{"id":1247,"type":"artist","name":"kazumu","url":"/artist/kazumu/","count":66},{"id":54385,"type":"artist","name":"minami chisato","url":"/artist/minami-chisato/","count":14},{"id":16408,"type":"artist","name":"miyahara ayumu","url":"/artist/miyahara-ayumu/","count":171},{"id":3285,"type":"artist","name":"momonosuke","url":"/artist/momonosuke/","count":205},{"id":21460,"type":"artist","name":"shigaoka touki","url":"/artist/shigaoka-touki/","count":65},{"id":1238,"type":"artist","name":"yu","url":"/artist/yu/","count":68},{"id":33173,"type":"category","name":"manga","url":"/category/manga/","count":77142},{"id":6346,"type":"language","name":"japanese","url":"/language/japanese/","count":191613}],"num_pages":253,"num_favorites":181}]}