{"result":[{"id":182319,"media_id":"1009683","title":{"english":"(C89) [RUBBISH Selecting Squad (Namonashi)] RE 23 (Fate/Grand Order) [English] [constantly]","japanese":"(C89) [RUBBISH\u9078\u5225\u968a (\u7121\u671b\u83dc\u5fd7)] RE23 (Fate/Grand Order) [\u82f1\u8a33]","pretty":"RE 23"},"images":{"pages":[{"t":"j","w":1280,"h":1790},{"t":"j","w":1280,"h":1873},{"t":"j","w":1280,"h":1842},{"t":"j","w":1280,"h":1842},{"t":"j","w":1280,"h":1827},{"t":"j","w":1280,"h":1830},{"t":"j","w":1280,"h":1827},{"t":"j","w":1280,"h":1832},{"t":"j","w":1280,"h":1827},{"t":"j","w":1280,"h":1835},{"t":"j","w":1280,"h":1827},{"t":"j","w":1280,"h":1836},{"t":"j","w":1280,"h":1827},{"t":"j","w":1280,"h":1841},{"t":"j","w":1280,"h":1832},{"t":"j","w":1280,"h":1844},{"t":"j","w":1280,"h":1832},{"t":"j","w":1280,"h":1841},{"t":"j","w":1280,"h":1827},{"t":"j","w":1280,"h":1838},{"t":"j","w":1280,"h":1827},{"t":"j","w":1280,"h":1827},{"t":"j","w":1280,"h":1827},{"t":"j","w":1280,"h":1827},{"t":"j","w":1280,"h":1827},{"t":"j","w":1280,"h":1827},{"t":"j","w":1280,"h":1827},{"t":"j","w":1280,"h":1827},{"t":"j","w":1000,"h":1733},{"t":"j","w":1280,"h":1790},{"t":"j","w":1280,"h":1809}],"cover":{"t":"j","w":350,"h":489},"thumbnail":{"t":"j","w":250,"h":350}},"scanlator":"","upload_date":1482710179,"tags":[{"id":14931,"type":"artist","name":"namonashi","url":"/artist/namonashi/","count":203},{"id":23264,"type":"group","name":"rubbish selecting squad","url":"/group/rubbish-selecting-squad/","count":107},{"id":14283,"type":"tag","name":"anal","url":"/tag/anal/","count":64587},{"id":9661,"type":"tag","name":"cervix penetration","url":"/tag/cervix-penetration/","count":2772},{"id":22945,"type":"tag","name":"double penetration","url":"/tag/double-penetration/","count":24472},{"id":8378,"type":"tag","name":"glasses","url":"/tag/glasses/","count":48279},{"id":24380,"type":"tag","name":"pantyhose","url":"/tag/pantyhose/","count":14713},{"id":31775,"type":"tag","name":"tentacles","url":"/tag/tentacles/","count":13276},{"id":19954,"type":"tag","name":"yuri","url":"/tag/yuri/","count":20241},{"id":12227,"type":"language","name":"english","url":"/language/english/","count":69378},{"id":17249,"type":"language","name":"translated","url":"/language/translated/","count":109734},{"id":35605,"type":"parody","name":"fate grand order","url":"/parody/fate-grand-order/","count":7900},{"id":33172,"type":"category","name":"doujinshi","url":"/category/doujinshi/","count":228729},{"id":51419,"type":"character","name":"gudako","url":"/character/gudako/","count":441},{"id":37739,"type":"character","name":"shielder","url":"/character/shielder/","count":972}],"num_pages":31,"num_favorites":1889},{"id":166831,"media_id":"945988","title":{"english":"(C89) [RUBBISH Selecting Squad (Namonashi)] RE 23 (Fate/Grand Order)","japanese":"(C89) [RUBBISH\u9078\u5225\u968a (\u7121\u671b\u83dc\u5fd7)] RE23 (Fate/Grand Order)","pretty":"RE 23"},"images":{"pages":[{"t":"j","w":1280,"h":1790},{"t":"p","w":1200,"h":1704},{"t":"j","w":1280,"h":1873},{"t":"j","w":1280,"h":1842},{"t":"j","w":1280,"h":1842},{"t":"j","w":1280,"h":1827},{"t":"j","w":1280,"h":1830},{"t":"j","w":1280,"h":1827},{"t":"j","w":1280,"h":1832},{"t":"j","w":1280,"h":1827},{"t":"j","w":1280,"h":1835},{"t":"j","w":1280,"h":1827},{"t":"j","w":1280,"h":1836},{"t":"j","w":1280,"h":1827},{"t":"j","w":1280,"h":1841},{"t":"j","w":1280,"h":1832},{"t":"j","w":1280,"h":1844},{"t":"j","w":1280,"h":1832},{"t":"j","w":1280,"h":1841},{"t":"j","w":1280,"h":1827},{"t":"j","w":1280,"h":1838},{"t":"j","w":1280,"h":1827},{"t":"j","w":1280,"h":1827},{"t":"j","w":1280,"h":1827},{"t":"j","w":1280,"h":1827},{"t":"j","w":1280,"h":1827},{"t":"j","w":1280,"h":1827},{"t":"j","w":1280,"h":1827},{"t":"j","w":1280,"h":1827},{"t":"j","w":1280,"h":1856},{"t":"j","w":1000,"h":1733},{"t":"j","w":1280,"h":1790}],"cover":{"t":"j","w":350,"h":489},"thumbnail":{"t":"j","w":250,"h":350}},"scanlator":"","upload_date":1466213819,"tags":[{"id":23264,"type":"group","name":"rubbish selecting squad","url":"/group/rubbish-selecting-squad/","count":107},{"id":14931,"type":"artist","name":"namonashi","url":"/artist/namonashi/","count":203},{"id":37739,"type":"character","name":"shielder","url":"/character/shielder/","count":995},{"id":14283,"type":"tag","name":"anal","url":"/tag/anal/","count":64587},{"id":22945,"type":"tag","name":"double penetration","url":"/tag/double-penetration/","count":24472},{"id":8378,"type":"tag","name":"glasses","url":"/tag/glasses/","count":48279},{"id":21989,"type":"tag","name":"inflation","url":"/tag/inflation/","count":5149},{"id":24380,"type":"tag","name":"pantyhose","url":"/tag/pantyhose/","count":14868},{"id":1590,"type":"tag","name":"sweating","url":"/tag/sweating/","count":7815},{"id":31775,"type":"tag","name":"tentacles","url":"/tag/tentacles/","count":13276},{"id":20035,"type":"tag","name":"x-ray","url":"/tag/x-ray/","count":20947},{"id":35605,"type":"parody","name":"fate grand order","url":"/parody/fate-grand-order/","count":7900},{"id":33172,"type":"category","name":"doujinshi","url":"/category/doujinshi/","count":228729},{"id":6346,"type":"language","name":"japanese","url":"/language/japanese/","count":191613},{"id":51419,"type":"character","name":"gudako","url":"/character/gudako/","count":451},{"id":9661,"type":"tag","name":"cervix penetration","url":"/tag/cervix-penetration/","count":2772},{"id":19954,"type":"tag","name":"yuri","url":"/tag/yuri/","count":20241},{"id":24102,"type":"tag","name":"lactation","url":"/tag/lactation/","count":11973}],"num_pages":32,"num_favorites":397},{"id":220015,"media_id":"1167027","title":{"english":"(COMIC1\u260611) [liz project (Miyamoto Liz)] Watashi no Kawaii Nasubi-chan | My Sweet Eggplant (Fate/Grand Order) [English] [Salty Hometown Boys]","japanese":"(COMIC1\u260611) [liz project (\u5bae\u672c\u308a\u305a)] \u308f\u305f\u3057\u306e\u304b\u308f\u3044\u3044\u306a\u3059\u3073\u3061\u3083\u3093 (Fate/Grand Order) [\u82f1\u8a33]","pretty":"Watashi no Kawaii Nasubi-chan | My Sweet Eggplant"},"images":{"pages":[{"t":"j","w":1280,"h":1828},{"t":"j","w":1280,"h":1830},{"t":"j","w":1280,"h":1829},{"t":"j","w":1280,"h":1832},{"t":"j","w":1280,"h":1829},{"t":"j","w":1280,"h":1828},{"t":"j","w":1280,"h":1826},{"t":"j","w":1280,"h":1829},{"t":"j","w":1280,"h":1829},{"t":"j","w":1280,"h":1828},{"t":"j","w":1280,"h":1828},{"t":"j","w":1280,"h":1826},{"t":"j","w":1280,"h":1827},{"t":"j","w":1280,"h":1832},{"t":"j","w":1280,"h":1828},{"t":"j","w":1280,"h":1830},{"t":"j","w":1280,"h":1828},{"t":"j","w":1280,"h":1835},{"t":"j","w":1200,"h":1633}],"cover":{"t":"j","w":350,"h":500},"thumbnail":{"t":"j","w":250,"h":357}},"scanlator":"","upload_date":1515500299,"tags":[{"id":1607,"type":"group","name":"liz project","url":"/group/liz-project/","count":38},{"id":12227,"type":"language","name":"english","url":"/language/english/","count":69378},{"id":17249,"type":"language","name":"translated","url":"/language/translated/","count":109734},{"id":27649,"type":"artist","name":"miyamoto liz","url":"/artist/miyamoto-liz/","count":81},{"id":51419,"type":"character","name":"gudako","url":"/character/gudako/","count":451},{"id":779,"type":"tag","name":"futanari","url":"/tag/futanari/","count":23173},{"id":8378,"type":"tag","name":"glasses","url":"/tag/glasses/","count":48279},{"id":24380,"type":"tag","name":"pantyhose","url":"/tag/pantyhose/","count":14868},{"id":16236,"type":"tag","name":"shemale","url":"/tag/shemale/","count":1938},{"id":35972,"type":"tag","name":"sole dickgirl","url":"/tag/sole-dickgirl/","count":2714},{"id":35762,"type":"tag","name":"sole female","url":"/tag/sole-female/","count":66202},{"id":35605,"type":"parody","name":"fate grand order","url":"/parody/fate-grand-order/","count":7900},{"id":33172,"type":"category","name":"doujinshi","url":"/category/doujinshi/","count":228729},{"id":37739,"type":"character","name":"shielder","url":"/character/shielder/","count":995},{"id":30035,"type":"tag","name":"gender bender","url":"/tag/gender-bender/","count":7497},{"id":30645,"type":"tag","name":"dick growth","url":"/tag/dick-growth/","count":3297},{"id":19954,"type":"tag","name":"yuri","url":"/tag/yuri/","count":20241}],"num_pages":19,"num_favorites":1696},{"id":"297656","media_id":"1552408","title":{"english":"(C97) [CELTRANCE (Kogaku Kazuya)] Massh Mash ni Shite yan yo (Fate/Grand Order)","japanese":"(C97) [CELTRANCE (\u864e\u984e\u304b\u305a\u3084)] \u307e\u3063\u3057\u3085\u307e\u3057\u3085\u306b\u30b7\u30c6\u3084\u3093\u3088 (Fate/Grand Order)","pretty":"Massh Mash ni Shite yan yo"},"images":{"pages":[{"t":"j","w":1280,"h":1819},{"t":"j","w":1280,"h":1814},{"t":"j","w":1280,"h":1814},{"t":"j","w":1280,"h":1814},{"t":"j","w":1280,"h":1814},{"t":"j","w":1280,"h":1814},{"t":"j","w":1280,"h":1814},{"t":"j","w":1280,"h":1814},{"t":"j","w":1280,"h":1814},{"t":"j","w":1280,"h":1814},{"t":"j","w":1280,"h":1814},{"t":"j","w":1280,"h":1814},{"t":"j","w":1280,"h":1814},{"t":"j","w":1280,"h":1814},{"t":"j","w":1280,"h":1814},{"t":"j","w":1280,"h":1814},{"t":"j","w":1280,"h":1814},{"t":"j","w":1280,"h":1814},{"t":"j","w":1280,"h":1814},{"t":"j","w":1280,"h":1814},{"t":"j","w":1280,"h":1814},{"t":"j","w":1280,"h":1819}],"cover":{"t":"j","w":350,"h":498},"thumbnail":{"t":"j","w":250,"h":356}},"scanlator":"","upload_date":1579023998,"tags":[{"id":35605,"type":"parody","name":"fate grand order","url":"/parody/fate-grand-order/","count":7900},{"id":9803,"type":"character","name":"saber alter","url":"/character/saber-alter/","count":205},{"id":27958,"type":"group","name":"celtrance","url":"/group/celtrance/","count":49},{"id":24193,"type":"artist","name":"kogaku kazuya","url":"/artist/kogaku-kazuya/","count":81},{"id":8050,"type":"tag","name":"females only","url":"/tag/females-only/","count":8656},{"id":8378,"type":"tag","name":"glasses","url":"/tag/glasses/","count":48279},{"id":24380,"type":"tag","name":"pantyhose","url":"/tag/pantyhose/","count":14713},{"id":85288,"type":"tag","name":"ponytail","url":"/tag/ponytail/","count":8011},{"id":19954,"type":"tag","name":"yuri","url":"/tag/yuri/","count":20241},{"id":33172,"type":"category","name":"doujinshi","url":"/category/doujinshi/","count":228729},{"id":6346,"type":"language","name":"japanese","url":"/language/japanese/","count":191613},{"id":37739,"type":"character","name":"shielder","url":"/character/shielder/","count":972},{"id":7155,"type":"tag","name":"cunnilingus","url":"/tag/cunnilingus/","count":4595}],"num_pages":22,"num_favorites":366},{"id":313803,"media_id":"1640105","title":{"english":"[THERMOSTAT (Neji)] Guda Joshi! (Fate/Grand Order) [Digital]","japanese":"[THERMOSTAT (\u5bdd\u8def)] \u3050\u3060\u3058\u3087\u3057! (Fate/Grand Order) [DL\u7248]","pretty":"Guda Joshi!"},"images":{"pages":[{"t":"j","w":1280,"h":925},{"t":"j","w":1280,"h":1746},{"t":"j","w":1280,"h":1746},{"t":"j","w":1280,"h":1746},{"t":"j","w":1280,"h":1746},{"t":"j","w":1280,"h":1746},{"t":"j","w":1280,"h":1746},{"t":"j","w":1280,"h":1746},{"t":"j","w":1280,"h":1746},{"t":"j","w":1280,"h":1746},{"t":"j","w":1280,"h":1746},{"t":"j","w":1280,"h":1746},{"t":"j","w":1280,"h":1746},{"t":"j","w":1280,"h":1746},{"t":"j","w":1280,"h":1746},{"t":"j","w":1280,"h":1746},{"t":"j","w":1280,"h":1746},{"t":"j","w":1280,"h":1746},{"t":"j","w":1280,"h":1746},{"t":"j","w":1280,"h":1746},{"t":"j","w":1280,"h":1746},{"t":"j","w":1280,"h":1746},{"t":"j","w":1280,"h":1746},{"t":"j","w":1280,"h":1746},{"t":"j","w":1280,"h":1746}],"cover":{"t":"j","w":350,"h":253},"thumbnail":{"t":"j","w":250,"h":180}},"scanlator":"","upload_date":1589840624,"tags":[{"id":35605,"type":"parody","name":"fate grand order","url":"/parody/fate-grand-order/","count":8383},{"id":51419,"type":"character","name":"gudako","url":"/character/gudako/","count":466},{"id":85371,"type":"group","name":"thermostat","url":"/group/thermostat/","count":6},{"id":85372,"type":"artist","name":"neji","url":"/artist/neji/","count":9},{"id":8050,"type":"tag","name":"females only","url":"/tag/females-only/","count":9021},{"id":19954,"type":"tag","name":"yuri","url":"/tag/yuri/","count":20769},{"id":33172,"type":"category","name":"doujinshi","url":"/category/doujinshi/","count":235353},{"id":6346,"type":"language","name":"japanese","url":"/language/japanese/","count":195391},{"id":37739,"type":"character","name":"shielder","url":"/character/shielder/","count":1017}],"num_pages":25,"num_favorites":223}]}