[{"id":1665484,"gallery_id":251291,"poster":{"id":3517199,"username":"kumomoto","slug":"kumomoto","avatar_url":"avatars/3517199.png?_=aabc91662c77185d","is_superuser":false,"is_staff":false},"post_date":1617790307,"body":"If you are reading this your parents will die in 5 years. To Undo this curse copy and paste onto 5 other manga If you are reading this comment your parents will die within 5 years. "},{"id":721171,"gallery_id":251291,"poster":{"id":82411,"username":"lolimasutah","slug":"lolimasutah","avatar_url":"avatars/82411.png?_=71d614b2206037d4","is_superuser":false,"is_staff":false},"post_date":1540760200,"body":"The six page sequence of Jun masturbating is really hot."}]