{"result":[{"id":288076,"media_id":"1500754","title":{"english":"[Malus Pumila (Umuga Yasusi)] Shi-a-wa-se (Fresh Precure) [Digital]","japanese":"[\u307e\u308b\u3059\u3077\u307f\u3089 (U\u7121\u6211\u4ec1)] \u3057\u30fb\u3042\u30fb\u308f\u30fb\u305b (\u30d5\u30ec\u30c3\u30b7\u30e5\u30d7\u30ea\u30ad\u30e5\u30a2) [DL\u7248]","pretty":"Shiwa-se"},"images":{"pages":[{"t":"j","w":1045,"h":1500},{"t":"j","w":1045,"h":1500},{"t":"j","w":1045,"h":1500},{"t":"j","w":1045,"h":1500},{"t":"j","w":1045,"h":1500},{"t":"j","w":1045,"h":1500},{"t":"j","w":1045,"h":1500},{"t":"j","w":1045,"h":1500},{"t":"j","w":1045,"h":1500},{"t":"j","w":1045,"h":1500},{"t":"j","w":1045,"h":1500},{"t":"j","w":1045,"h":1500},{"t":"j","w":1045,"h":1500},{"t":"j","w":1045,"h":1500},{"t":"j","w":1045,"h":1500},{"t":"j","w":1045,"h":1500},{"t":"j","w":1045,"h":1500},{"t":"j","w":1045,"h":1500},{"t":"j","w":1045,"h":1500},{"t":"j","w":1045,"h":1500},{"t":"j","w":1045,"h":1500},{"t":"j","w":1045,"h":1500},{"t":"j","w":1045,"h":1500},{"t":"j","w":1045,"h":1500}],"cover":{"t":"j","w":350,"h":502},"thumbnail":{"t":"j","w":250,"h":359}},"scanlator":"","upload_date":1570994876,"tags":[{"id":112363,"type":"artist","name":"umuga yasusi","url":"/artist/umuga-yasusi/","count":4},{"id":706,"type":"tag","name":"birth","url":"/tag/birth/","count":2633},{"id":8050,"type":"tag","name":"females only","url":"/tag/females-only/","count":8765},{"id":6343,"type":"tag","name":"pregnant","url":"/tag/pregnant/","count":9243},{"id":33172,"type":"category","name":"doujinshi","url":"/category/doujinshi/","count":228729},{"id":6346,"type":"language","name":"japanese","url":"/language/japanese/","count":191613},{"id":28004,"type":"parody","name":"fresh precure","url":"/parody/fresh-precure/","count":203},{"id":14817,"type":"character","name":"cure passion","url":"/character/cure-passion/","count":34},{"id":8884,"type":"character","name":"cure peach","url":"/character/cure-peach/","count":54},{"id":112153,"type":"group","name":"malus pumila","url":"/group/malus-pumila/","count":4},{"id":19954,"type":"tag","name":"yuri","url":"/tag/yuri/","count":20241}],"num_pages":24,"num_favorites":105},{"id":297119,"media_id":"1549992","title":{"english":"[Malus Pumila (Umuga Yasusi)] Hanataba o, Kimi ni (Love Live!) [Digital]","japanese":"[\u307e\u308b\u3059\u3077\u307f\u3089 (U\u7121\u6211\u4ec1)] \u82b1\u675f\u3092\u3001\u541b\u306b (\u30e9\u30d6\u30e9\u30a4\u30d6!) [DL\u7248]","pretty":"Hanataba o, Kimi ni"},"images":{"pages":[{"t":"j","w":1280,"h":1780},{"t":"j","w":1280,"h":1780},{"t":"j","w":1280,"h":1780},{"t":"j","w":1280,"h":1780},{"t":"j","w":1280,"h":1780},{"t":"j","w":1280,"h":1780},{"t":"j","w":1280,"h":1780},{"t":"j","w":1280,"h":1780},{"t":"j","w":1280,"h":1780},{"t":"j","w":1280,"h":1780},{"t":"j","w":1280,"h":1780},{"t":"j","w":1280,"h":1780},{"t":"j","w":1280,"h":1780},{"t":"j","w":1280,"h":1780},{"t":"j","w":1280,"h":1780},{"t":"j","w":1280,"h":1780},{"t":"j","w":1280,"h":1780},{"t":"j","w":1280,"h":1780},{"t":"j","w":1280,"h":1780},{"t":"j","w":1280,"h":1780},{"t":"j","w":1280,"h":1780},{"t":"j","w":1280,"h":1780},{"t":"j","w":1280,"h":1780},{"t":"j","w":1280,"h":1780},{"t":"j","w":1280,"h":1780},{"t":"j","w":1280,"h":1780}],"cover":{"t":"j","w":350,"h":486},"thumbnail":{"t":"j","w":250,"h":348}},"scanlator":"","upload_date":1578696963,"tags":[{"id":3185,"type":"parody","name":"love live","url":"/parody/love-live/","count":2120},{"id":75029,"type":"character","name":"eli ayase","url":"/character/eli-ayase/","count":194},{"id":75102,"type":"character","name":"nozomi tojo","url":"/character/nozomi-tojo/","count":138},{"id":112153,"type":"group","name":"malus pumila","url":"/group/malus-pumila/","count":4},{"id":112363,"type":"artist","name":"umuga yasusi","url":"/artist/umuga-yasusi/","count":4},{"id":706,"type":"tag","name":"birth","url":"/tag/birth/","count":2609},{"id":8050,"type":"tag","name":"females only","url":"/tag/females-only/","count":8656},{"id":6343,"type":"tag","name":"pregnant","url":"/tag/pregnant/","count":9150},{"id":19954,"type":"tag","name":"yuri","url":"/tag/yuri/","count":20241},{"id":33172,"type":"category","name":"doujinshi","url":"/category/doujinshi/","count":228729},{"id":6346,"type":"language","name":"japanese","url":"/language/japanese/","count":191613},{"id":14971,"type":"tag","name":"sex toys","url":"/tag/sex-toys/","count":20823}],"num_pages":26,"num_favorites":270},{"id":289364,"media_id":"1507842","title":{"english":"[Malus Pumila (Umuga Yasusi)] Yoshiko no Fukuin (Love Live! Sunshine!!) [Digital]","japanese":"[\u307e\u308b\u3059\u3077\u307f\u3089 (U\u7121\u6211\u4ec1)] \u5584\u5b50\u306e\u798f\u97f3 (\u30e9\u30d6\u30e9\u30a4\u30d6! \u30b5\u30f3\u30b7\u30e3\u30a4\u30f3!!) [DL\u7248]","pretty":"Yoshiko no Fukuin"},"images":{"pages":[{"t":"j","w":1280,"h":905},{"t":"j","w":1280,"h":1811},{"t":"j","w":1280,"h":1811},{"t":"j","w":1280,"h":1811},{"t":"j","w":1280,"h":1811},{"t":"j","w":1280,"h":1811},{"t":"j","w":1280,"h":1811},{"t":"j","w":1280,"h":1811},{"t":"j","w":1280,"h":1811},{"t":"j","w":1280,"h":1811},{"t":"j","w":1280,"h":1811},{"t":"j","w":1280,"h":1811},{"t":"j","w":1280,"h":1811},{"t":"j","w":1280,"h":1811},{"t":"j","w":1280,"h":1811},{"t":"j","w":1280,"h":1811},{"t":"j","w":1280,"h":1811},{"t":"j","w":1280,"h":1811},{"t":"j","w":1280,"h":1811},{"t":"j","w":1280,"h":1811},{"t":"j","w":1280,"h":1811}],"cover":{"t":"j","w":350,"h":248},"thumbnail":{"t":"j","w":250,"h":177}},"scanlator":"","upload_date":1572205934,"tags":[{"id":37544,"type":"parody","name":"love live sunshine","url":"/parody/love-live-sunshine/","count":798},{"id":50944,"type":"character","name":"yoshiko tsushima","url":"/character/yoshiko-tsushima/","count":173},{"id":112153,"type":"group","name":"malus pumila","url":"/group/malus-pumila/","count":4},{"id":112363,"type":"artist","name":"umuga yasusi","url":"/artist/umuga-yasusi/","count":4},{"id":706,"type":"tag","name":"birth","url":"/tag/birth/","count":2633},{"id":29224,"type":"tag","name":"impregnation","url":"/tag/impregnation/","count":15618},{"id":6343,"type":"tag","name":"pregnant","url":"/tag/pregnant/","count":9243},{"id":10314,"type":"tag","name":"schoolgirl uniform","url":"/tag/schoolgirl-uniform/","count":56614},{"id":33172,"type":"category","name":"doujinshi","url":"/category/doujinshi/","count":231184},{"id":6346,"type":"language","name":"japanese","url":"/language/japanese/","count":193003},{"id":106733,"type":"tag","name":"hair buns","url":"/tag/hair-buns/","count":554}],"num_pages":21,"num_favorites":129},{"id":350406,"media_id":"1862590","title":{"english":"[Hentai-san] Matsu \uffee Aya No Shussan","japanese":"[\u5909\u614b\u3055\u3093] \u677e\u25cb\u4e9c\u5f25\u306e\u51fa\u7523","pretty":"Matsu \uffee Aya No Shussan"},"images":{"pages":[{"t":"j","w":500,"h":667},{"t":"j","w":500,"h":667},{"t":"j","w":500,"h":667},{"t":"j","w":500,"h":667},{"t":"j","w":500,"h":667},{"t":"j","w":500,"h":667},{"t":"j","w":500,"h":667},{"t":"j","w":500,"h":667},{"t":"j","w":500,"h":667},{"t":"j","w":500,"h":667},{"t":"j","w":500,"h":667},{"t":"j","w":500,"h":667},{"t":"j","w":500,"h":667},{"t":"j","w":500,"h":667},{"t":"j","w":500,"h":667},{"t":"j","w":500,"h":667},{"t":"j","w":500,"h":667},{"t":"j","w":500,"h":667},{"t":"j","w":500,"h":667},{"t":"j","w":500,"h":667}],"cover":{"t":"j","w":350,"h":467},"thumbnail":{"t":"j","w":250,"h":334}},"scanlator":"","upload_date":1615108977,"tags":[{"id":706,"type":"tag","name":"birth","url":"/tag/birth/","count":2990},{"id":6343,"type":"tag","name":"pregnant","url":"/tag/pregnant/","count":10368},{"id":6346,"type":"language","name":"japanese","url":"/language/japanese/","count":211120},{"id":8050,"type":"tag","name":"females only","url":"/tag/females-only/","count":10277},{"id":33172,"type":"category","name":"doujinshi","url":"/category/doujinshi/","count":263739},{"id":90671,"type":"parody","name":"original","url":"/parody/original/","count":33864}],"num_pages":20,"num_favorites":73},{"id":223035,"media_id":"1179644","title":{"english":"(C93) [Nyan Nyan Nyan! (Ogawa Hidari)] Inochi no Kakera (Made in Abyss)","japanese":"(C93) [\u306b\u3083\u3093\u306b\u3083\u3093\u306b\u3083\u3093! (\u5c0f\u5ddd\u3072\u3060\u308a)] \u3044\u306e\u3061\u306e\u304b\u3051\u3089 (\u30e1\u30a4\u30c9\u30a4\u30f3\u30a2\u30d3\u30b9)","pretty":"Inochi no Kakera"},"images":{"pages":[{"t":"j","w":1280,"h":1814},{"t":"j","w":1280,"h":1809},{"t":"j","w":1280,"h":1829},{"t":"j","w":1280,"h":1829},{"t":"j","w":1280,"h":1829},{"t":"j","w":1280,"h":1829},{"t":"j","w":1280,"h":1829},{"t":"j","w":1280,"h":1834},{"t":"j","w":1280,"h":1829},{"t":"j","w":1280,"h":1829},{"t":"j","w":1280,"h":1828},{"t":"j","w":1280,"h":1829},{"t":"j","w":1280,"h":1829},{"t":"j","w":1280,"h":1829},{"t":"j","w":1280,"h":1829},{"t":"j","w":1280,"h":1829},{"t":"j","w":1280,"h":1822},{"t":"j","w":1280,"h":1822},{"t":"j","w":1280,"h":1823},{"t":"j","w":1280,"h":1822},{"t":"j","w":1280,"h":1822},{"t":"j","w":1280,"h":1822},{"t":"j","w":1280,"h":1822},{"t":"j","w":1280,"h":1822},{"t":"j","w":1280,"h":1822},{"t":"j","w":1280,"h":1823},{"t":"j","w":1280,"h":1822},{"t":"j","w":1280,"h":1822},{"t":"j","w":1280,"h":1822},{"t":"j","w":1280,"h":1822},{"t":"j","w":1280,"h":1822},{"t":"j","w":1280,"h":1822},{"t":"j","w":1280,"h":1822},{"t":"j","w":1280,"h":1822},{"t":"j","w":1280,"h":1822},{"t":"j","w":1280,"h":1822},{"t":"j","w":1280,"h":1822},{"t":"j","w":1280,"h":1822},{"t":"j","w":1280,"h":1825},{"t":"j","w":1280,"h":1825},{"t":"j","w":1280,"h":1825},{"t":"j","w":1280,"h":1826},{"t":"j","w":1280,"h":1826},{"t":"j","w":1280,"h":1825},{"t":"j","w":1280,"h":1825},{"t":"j","w":1280,"h":1826},{"t":"j","w":1280,"h":1826},{"t":"j","w":1280,"h":1825},{"t":"j","w":1280,"h":1826},{"t":"j","w":1280,"h":1825},{"t":"j","w":1280,"h":1825},{"t":"j","w":1280,"h":1825},{"t":"j","w":1280,"h":1825},{"t":"j","w":1280,"h":1825},{"t":"j","w":1280,"h":1825},{"t":"j","w":1280,"h":1825},{"t":"j","w":1280,"h":1825},{"t":"j","w":1280,"h":1825}],"cover":{"t":"j","w":350,"h":496},"thumbnail":{"t":"j","w":250,"h":354}},"scanlator":"","upload_date":1517713624,"tags":[{"id":18983,"type":"group","name":"nyan nyan nyan","url":"/group/nyan-nyan-nyan/","count":23},{"id":14584,"type":"artist","name":"ogawa hidari","url":"/artist/ogawa-hidari/","count":56},{"id":75810,"type":"character","name":"ozen","url":"/character/ozen/","count":17},{"id":706,"type":"tag","name":"birth","url":"/tag/birth/","count":2609},{"id":8050,"type":"tag","name":"females only","url":"/tag/females-only/","count":8656},{"id":29224,"type":"tag","name":"impregnation","url":"/tag/impregnation/","count":15414},{"id":6343,"type":"tag","name":"pregnant","url":"/tag/pregnant/","count":9150},{"id":19954,"type":"tag","name":"yuri","url":"/tag/yuri/","count":20241},{"id":75713,"type":"parody","name":"made in abyss","url":"/parody/made-in-abyss/","count":62},{"id":33172,"type":"category","name":"doujinshi","url":"/category/doujinshi/","count":228729},{"id":6346,"type":"language","name":"japanese","url":"/language/japanese/","count":191613}],"num_pages":58,"num_favorites":395}]}