[{"id":2534615,"gallery_id":325352,"poster":{"id":4046717,"username":"canislupus21","slug":"canislupus21","avatar_url":"avatars/4046717.png?_=b87edc684f887453","is_superuser":false,"is_staff":false},"post_date":1652904709,"body":"Nice!       "},{"id":1536958,"gallery_id":325352,"poster":{"id":3449554,"username":"Indomie goreng 2500","slug":"indomie-goreng-2500","avatar_url":"avatars/3449554.png?_=dc93e89251be640d","is_superuser":false,"is_staff":false},"post_date":1612082136,"body":"this is poggers"},{"id":1380425,"gallery_id":325352,"poster":{"id":224986,"username":"mikeyphalanx","slug":"mikeyphalanx","avatar_url":"avatars/pastamania.png","is_superuser":false,"is_staff":false},"post_date":1606980875,"body":"Chiyuki: Perverted onee-san. \nRinze: Perverted okaa-san.\n\nWho's next? \ud83d\ude02 Hope to see a continuation. \ud83d\ude02"},{"id":1364621,"gallery_id":325352,"poster":{"id":1611670,"username":"Kikusama","slug":"kikusama","avatar_url":"avatars/1611670.png?_=f01f461e96158443","is_superuser":false,"is_staff":false},"post_date":1606418239,"body":"We need more chiyuki"},{"id":1276520,"gallery_id":325352,"poster":{"id":1910563,"username":"IchiHimeKUROSAKI","slug":"ichihimekurosaki","avatar_url":"avatars/1910563.png","is_superuser":false,"is_staff":false},"post_date":1602917555,"body":"Whats next? Peverted Imouto? Well........ it better be haha "},{"id":1160299,"gallery_id":325352,"poster":{"id":1785332,"username":"HentaiRouge","slug":"hentairouge","avatar_url":"avatars/1785332.png","is_superuser":false,"is_staff":false},"post_date":1597946792,"body":"Affection:\u221e"},{"id":1157730,"gallery_id":325352,"poster":{"id":3347808,"username":"Doomslayer (Doomguy)","slug":"doomslayer-doomguy","avatar_url":"avatars/3347808.png?_=2a6ad81a4bfa2151","is_superuser":false,"is_staff":false},"post_date":1597861562,"body":"To download you need to delete your account "},{"id":1157476,"gallery_id":325352,"poster":{"id":3564049,"username":"NauSing","slug":"nausing","avatar_url":"avatars/pastamania.png","is_superuser":false,"is_staff":false},"post_date":1597853569,"body":"how to download"},{"id":1157371,"gallery_id":325352,"poster":{"id":849875,"username":"Wolf of the Saturn Six","slug":"wolf-of-the-saturn-six","avatar_url":"avatars/849875.png","is_superuser":false,"is_staff":false},"post_date":1597851372,"body":"CHIYUKI MY WAAAYFFFF!!!"}]