[{"id":1438050,"gallery_id":341319,"poster":{"id":3868218,"username":"R3gular","slug":"r3gular","avatar_url":"avatars/3868218.png?_=214b972b3c7ef9a4","is_superuser":false,"is_staff":false},"post_date":1609126136,"body":"My poor doutei just never gets a break, he just wana turn into a wizard godamn"},{"id":1434868,"gallery_id":341319,"poster":{"id":3761139,"username":"felixshota","slug":"felixshota","avatar_url":"avatars/pastamania.png","is_superuser":false,"is_staff":false},"post_date":1609024657,"body":"WOOOOO AKINA AND AIZONO DOUJIN\nFINALLY\n"},{"id":1432771,"gallery_id":341319,"poster":{"id":3946576,"username":"Bruhman69","slug":"bruhman69","avatar_url":"avatars/pastamania.png","is_superuser":false,"is_staff":false},"post_date":1608953972,"body":"If you are reading this comment your parents will die within 5 years. To undo this curse you need to copy this and paste it on 5 other manga. i'm so, so sorry,please forgive me. I Know this may be seem nonsense but not gonna risk"}]