[{"id":1580400,"gallery_id":343907,"poster":{"id":3284610,"username":"gkcvjcf","slug":"gkcvjcf","avatar_url":"avatars/pastamania.png","is_superuser":false,"is_staff":false},"post_date":1613999789,"body":"wish there was a english translate\n"},{"id":1528331,"gallery_id":343907,"poster":{"id":3863541,"username":"Onichan01","slug":"onichan01","avatar_url":"avatars/3863541.png?_=d3cb0bb4bebfbf5b","is_superuser":false,"is_staff":false},"post_date":1611696134,"body":"This art is super the last page with that ass IS AMAZING it should not stop at that page.Very talented artist it should also do some anal scenes"},{"id":1506460,"gallery_id":343907,"poster":{"id":3563751,"username":"Tom Nathan","slug":"tom-nathan","avatar_url":"avatars/3563751.png?_=4a0897776793266f","is_superuser":false,"is_staff":false},"post_date":1610806328,"body":"This is better than man with loli! Shota and loli is poggers!"},{"id":1487897,"gallery_id":343907,"poster":{"id":208467,"username":"edersiyo","slug":"edersiyo","avatar_url":"avatars/208467.png","is_superuser":false,"is_staff":false},"post_date":1610654154,"body":"needs the incest tag "},{"id":1487620,"gallery_id":343907,"poster":{"id":2858547,"username":"FBI-sama","slug":"fbi-sama","avatar_url":"avatars/2858547.png?_=7a0662e30745046a","is_superuser":false,"is_staff":false},"post_date":1610644536,"body":"I dont know how to say it Citizen-kun, but its confusing me from the part where the art is perfect but..... Oh well, gotta follow rules!"},{"id":1487611,"gallery_id":343907,"poster":{"id":1299331,"username":"alonerone","slug":"alonerone","avatar_url":"avatars/1299331.png","is_superuser":false,"is_staff":false},"post_date":1610644259,"body":"Still ongoing? D:"},{"id":1487414,"gallery_id":343907,"poster":{"id":3195332,"username":"Dickatron9000","slug":"dickatron9000","avatar_url":"avatars/pastamania.png","is_superuser":false,"is_staff":false},"post_date":1610638658,"body":"Its awesome! please keep on doing more!"},{"id":1486967,"gallery_id":343907,"poster":{"id":4014240,"username":"Hyong","slug":"hyong","avatar_url":"avatars/4014240.png?_=479413a5f3a7578f","is_superuser":false,"is_staff":false},"post_date":1610625028,"body":"God this is fucking good. We need more. "},{"id":1486662,"gallery_id":343907,"poster":{"id":2593941,"username":"KnowledgeDB","slug":"knowledgedb","avatar_url":"avatars/2593941.png?_=e50af288f98f523e","is_superuser":false,"is_staff":false},"post_date":1610612984,"body":"This is clearly incomplete. I need more of it. "},{"id":1486446,"gallery_id":343907,"poster":{"id":2172403,"username":"ImaAnimal","slug":"imaanimal","avatar_url":"avatars/2172403.png?_=e2132426feebd61c","is_superuser":false,"is_staff":false},"post_date":1610606685,"body":"very epic     "},{"id":1485925,"gallery_id":343907,"poster":{"id":3819682,"username":"reiskuchen","slug":"reiskuchen","avatar_url":"avatars/pastamania.png","is_superuser":false,"is_staff":false},"post_date":1610589712,"body":"Plss we need more"},{"id":1485827,"gallery_id":343907,"poster":{"id":3342862,"username":"Kazuki94","slug":"kazuki94","avatar_url":"avatars/3342862.png?_=73cc3419e168b31b","is_superuser":false,"is_staff":false},"post_date":1610586884,"body":"God this art is good\n"},{"id":1485483,"gallery_id":343907,"poster":{"id":3092014,"username":"BENTHOS","slug":"benthos","avatar_url":"avatars/3092014.png?_=8d1bda19cefd8477","is_superuser":false,"is_staff":false},"post_date":1610575064,"body":"I want a english version\ud83d\ude2d\ud83d\ude2d"}]