[{"id":2075892,"gallery_id":353273,"poster":{"id":1000463,"username":"\u32f1Quetz\u0e2alc\u00f8\u0e2atl\u32f1","slug":"quetzslcostl","avatar_url":"avatars/1000463.png?_=84499f0cbc07f8a1","is_superuser":false,"is_staff":false},"post_date":1633988566,"body":"The bloody nose was a major turn off"},{"id":2075878,"gallery_id":353273,"poster":{"id":1000463,"username":"\u32f1Quetz\u0e2alc\u00f8\u0e2atl\u32f1","slug":"quetzslcostl","avatar_url":"avatars/1000463.png?_=84499f0cbc07f8a1","is_superuser":false,"is_staff":false},"post_date":1633987811,"body":"@Secret Faggot Of The South \ud83d\ude02"},{"id":2073140,"gallery_id":353273,"poster":{"id":2583013,"username":"Secret Faggot Of The South","slug":"secret-faggot-of-the-south","avatar_url":"avatars/2583013.png","is_superuser":false,"is_staff":false},"post_date":1633883586,"body":"Damn... I wish I had a childhood friend that I can make love to in the ass "},{"id":1683506,"gallery_id":353273,"poster":{"id":1314354,"username":"formula","slug":"formula","avatar_url":"avatars/1314354.png?_=28d2a74abb629902","is_superuser":false,"is_staff":false},"post_date":1618660038,"body":"I like style articles \ud83d\ude1c"},{"id":1678834,"gallery_id":353273,"poster":{"id":444271,"username":"B\u034a\u0350\u0353\u0355u\u034d\u032a\u0332s\u0351\u0314\u0311\u0365\u0332\u0320\u033c\u0316s\u0364\u0350\u0367\u030d\u0357\u0353\u0353\u032d\u032e\u0325y","slug":"b-u-s-s-y","avatar_url":"avatars/444271.png","is_superuser":false,"is_staff":false},"post_date":1618421628,"body":"Really nice art"},{"id":1654935,"gallery_id":353273,"poster":{"id":41629,"username":"ninjinchan","slug":"ninjinchan","avatar_url":"avatars/41629.png?_=7d4791707416b330","is_superuser":false,"is_staff":false},"post_date":1617322544,"body":"absolutely erect over this"},{"id":1649919,"gallery_id":353273,"poster":{"id":36074,"username":"Neo_king","slug":"neo_king","avatar_url":"avatars/36074.png","is_superuser":false,"is_staff":false},"post_date":1617106615,"body":"Somebody translate this!"}]