[{"id":2522711,"gallery_id":402894,"poster":{"id":3756010,"username":"kcj998","slug":"kcj998","avatar_url":"avatars/3756010.png?_=57ab4f0bd6a693cd","is_superuser":false,"is_staff":false},"post_date":1652466991,"body":"\u6211\u771f\u7684\u662f\u793e\u4fdd\u554a\ud83d\ude0d\ud83d\ude0d\ud83d\ude0d"},{"id":2520542,"gallery_id":402894,"poster":{"id":1132359,"username":"Joako20","slug":"joako20","avatar_url":"avatars/1132359.png?_=7fcd52c6eee781a5","is_superuser":false,"is_staff":false},"post_date":1652387042,"body":"English pleaseee"}]