{"result":[{"id":154461,"media_id":"894749","title":{"english":"[Komiya Yuuta] Haru Oboro (Manga Bangaichi 2015-09) [English] {NecroManCr}","japanese":"[\u5c0f\u5bae\u88d5\u592a] \u6625\u6727 (\u6f2b\u753b\u3070\u3093\u304c\u3044\u3061 2015\u5e749\u6708\u53f7) [\u82f1\u8a33]","pretty":"Haru Oboro"},"images":{"pages":[{"t":"j","w":1200,"h":1748},{"t":"j","w":1200,"h":1762},{"t":"j","w":1200,"h":1744},{"t":"j","w":1200,"h":1754},{"t":"j","w":1200,"h":1746},{"t":"j","w":1200,"h":1763},{"t":"j","w":1200,"h":1762},{"t":"j","w":1200,"h":1762},{"t":"j","w":1200,"h":1744},{"t":"j","w":1200,"h":1750},{"t":"j","w":1200,"h":1746},{"t":"j","w":1200,"h":1751},{"t":"j","w":1200,"h":1741},{"t":"j","w":1200,"h":1749},{"t":"j","w":1200,"h":1746},{"t":"j","w":1200,"h":1749}],"cover":{"t":"j","w":350,"h":510},"thumbnail":{"t":"j","w":250,"h":364}},"scanlator":"","upload_date":1452983090,"tags":[{"id":24764,"type":"tag","name":"drunk","url":"/tag/drunk/","count":2227},{"id":8378,"type":"tag","name":"glasses","url":"/tag/glasses/","count":48279},{"id":28550,"type":"tag","name":"teacher","url":"/tag/teacher/","count":9616},{"id":27473,"type":"tag","name":"mosaic censorship","url":"/tag/mosaic-censorship/","count":23707},{"id":20525,"type":"tag","name":"defloration","url":"/tag/defloration/","count":23209},{"id":10314,"type":"tag","name":"schoolgirl uniform","url":"/tag/schoolgirl-uniform/","count":56168},{"id":12227,"type":"language","name":"english","url":"/language/english/","count":69378},{"id":17249,"type":"language","name":"translated","url":"/language/translated/","count":109734},{"id":20013,"type":"artist","name":"komiya yuuta","url":"/artist/komiya-yuuta/","count":65},{"id":33173,"type":"category","name":"manga","url":"/category/manga/","count":77142}],"num_pages":16,"num_favorites":730},{"id":154656,"media_id":"895406","title":{"english":"[Komiya Yuuta] Childhood Princess (Dreamsicle) [English] [Krozam]","japanese":"[\u5c0f\u5bae\u88d5\u592a] Childhood Princess (Dreamsicle) [\u82f1\u8a33]","pretty":"Childhood Princess"},"images":{"pages":[{"t":"j","w":1106,"h":1600},{"t":"j","w":1106,"h":1600},{"t":"j","w":1106,"h":1600},{"t":"j","w":1106,"h":1600},{"t":"j","w":1106,"h":1600},{"t":"j","w":1106,"h":1600},{"t":"j","w":1106,"h":1600},{"t":"j","w":1106,"h":1600},{"t":"j","w":1106,"h":1600},{"t":"j","w":1106,"h":1600},{"t":"j","w":1106,"h":1600},{"t":"j","w":1106,"h":1600},{"t":"j","w":1106,"h":1600},{"t":"j","w":1106,"h":1600},{"t":"j","w":1106,"h":1600},{"t":"j","w":1106,"h":1600},{"t":"j","w":1106,"h":1600},{"t":"j","w":1106,"h":1600},{"t":"j","w":1106,"h":1600},{"t":"j","w":1106,"h":1600},{"t":"j","w":1106,"h":1600},{"t":"j","w":1106,"h":1600},{"t":"j","w":1106,"h":1600},{"t":"j","w":1106,"h":1600},{"t":"j","w":1106,"h":1600},{"t":"j","w":1106,"h":1600},{"t":"j","w":1106,"h":1600},{"t":"j","w":1106,"h":1600},{"t":"j","w":1106,"h":1600},{"t":"j","w":1106,"h":1600},{"t":"j","w":1106,"h":1600},{"t":"j","w":1106,"h":1600},{"t":"j","w":1106,"h":1600},{"t":"j","w":1106,"h":1600},{"t":"j","w":1106,"h":1600},{"t":"j","w":1106,"h":1600},{"t":"j","w":1122,"h":1600}],"cover":{"t":"j","w":350,"h":506},"thumbnail":{"t":"j","w":250,"h":362}},"scanlator":"","upload_date":1453227021,"tags":[{"id":7752,"type":"tag","name":"schoolboy uniform","url":"/tag/schoolboy-uniform/","count":12400},{"id":35763,"type":"tag","name":"sole male","url":"/tag/sole-male/","count":60070},{"id":28800,"type":"tag","name":"bloomers","url":"/tag/bloomers/","count":5672},{"id":20525,"type":"tag","name":"defloration","url":"/tag/defloration/","count":23209},{"id":10314,"type":"tag","name":"schoolgirl uniform","url":"/tag/schoolgirl-uniform/","count":56168},{"id":35762,"type":"tag","name":"sole female","url":"/tag/sole-female/","count":66202},{"id":12227,"type":"language","name":"english","url":"/language/english/","count":69378},{"id":17249,"type":"language","name":"translated","url":"/language/translated/","count":109734},{"id":20013,"type":"artist","name":"komiya yuuta","url":"/artist/komiya-yuuta/","count":65},{"id":33173,"type":"category","name":"manga","url":"/category/manga/","count":77142}],"num_pages":37,"num_favorites":676},{"id":210694,"media_id":"1122995","title":{"english":"[Komiya Yuuta] Childhood Princess (Dreamsicle) [English] [Krozam] [Decensored]","japanese":"[\u5c0f\u5bae\u88d5\u592a] Childhood Princess (Dreamsicle) [\u82f1\u8a33] [\u7121\u4fee\u6b63]","pretty":"Childhood Princess"},"images":{"pages":[{"t":"j","w":1106,"h":1600},{"t":"j","w":1106,"h":1600},{"t":"j","w":1106,"h":1600},{"t":"j","w":1106,"h":1600},{"t":"j","w":1106,"h":1600},{"t":"j","w":1106,"h":1600},{"t":"j","w":1106,"h":1600},{"t":"j","w":1106,"h":1600},{"t":"j","w":1106,"h":1600},{"t":"j","w":1106,"h":1600},{"t":"j","w":1106,"h":1600},{"t":"j","w":1106,"h":1600},{"t":"j","w":1106,"h":1600},{"t":"j","w":1106,"h":1600},{"t":"j","w":1106,"h":1600},{"t":"j","w":1106,"h":1600},{"t":"j","w":1106,"h":1600},{"t":"j","w":1106,"h":1600},{"t":"j","w":1106,"h":1600},{"t":"j","w":1106,"h":1600},{"t":"j","w":1106,"h":1600},{"t":"j","w":1106,"h":1600},{"t":"j","w":1106,"h":1600},{"t":"j","w":1106,"h":1600},{"t":"j","w":1106,"h":1600},{"t":"j","w":1106,"h":1600},{"t":"j","w":1106,"h":1600},{"t":"j","w":1106,"h":1600},{"t":"j","w":1106,"h":1600},{"t":"j","w":1106,"h":1600},{"t":"j","w":1106,"h":1600},{"t":"j","w":1106,"h":1600},{"t":"j","w":1106,"h":1600},{"t":"j","w":1106,"h":1600},{"t":"j","w":1106,"h":1600},{"t":"j","w":1106,"h":1600},{"t":"j","w":1122,"h":1600}],"cover":{"t":"j","w":350,"h":506},"thumbnail":{"t":"j","w":250,"h":362}},"scanlator":"","upload_date":1507490684,"tags":[{"id":7752,"type":"tag","name":"schoolboy uniform","url":"/tag/schoolboy-uniform/","count":12311},{"id":35763,"type":"tag","name":"sole male","url":"/tag/sole-male/","count":60070},{"id":8693,"type":"tag","name":"uncensored","url":"/tag/uncensored/","count":7295},{"id":28800,"type":"tag","name":"bloomers","url":"/tag/bloomers/","count":5648},{"id":20525,"type":"tag","name":"defloration","url":"/tag/defloration/","count":23209},{"id":10314,"type":"tag","name":"schoolgirl uniform","url":"/tag/schoolgirl-uniform/","count":56168},{"id":35762,"type":"tag","name":"sole female","url":"/tag/sole-female/","count":66202},{"id":12227,"type":"language","name":"english","url":"/language/english/","count":69378},{"id":17249,"type":"language","name":"translated","url":"/language/translated/","count":109734},{"id":20013,"type":"artist","name":"komiya yuuta","url":"/artist/komiya-yuuta/","count":65},{"id":33173,"type":"category","name":"manga","url":"/category/manga/","count":77142}],"num_pages":37,"num_favorites":1245},{"id":148107,"media_id":"868845","title":{"english":"[Komiya Yuuta] Candy Puff Shokai Genteiban + Mini Art Collection [Chinese] [\u7121\u90aa\u6c17\u6f22\u5316\u7d44]","japanese":"[\u5c0f\u5bae\u88d5\u592a] Candy Puff \u521d\u56de\u9650\u5b9a\u7248 + \u30df\u30cb\u753b\u96c6 [\u4e2d\u56fd\u7ffb\u8a33]","pretty":"Candy Puff Shokai Genteiban + Mini Art Collection"},"images":{"pages":[{"t":"j","w":1200,"h":539},{"t":"j","w":1200,"h":539},{"t":"j","w":1200,"h":539},{"t":"j","w":1200,"h":148},{"t":"j","w":1200,"h":1724},{"t":"j","w":1200,"h":1724},{"t":"j","w":1200,"h":1724},{"t":"j","w":1200,"h":1724},{"t":"j","w":1200,"h":1743},{"t":"j","w":1200,"h":1743},{"t":"j","w":1200,"h":1743},{"t":"j","w":1200,"h":1743},{"t":"j","w":1200,"h":1743},{"t":"j","w":1200,"h":1743},{"t":"j","w":1200,"h":1743},{"t":"j","w":1200,"h":1743},{"t":"j","w":1200,"h":1743},{"t":"j","w":1200,"h":1743},{"t":"j","w":1200,"h":1743},{"t":"j","w":1200,"h":1743},{"t":"j","w":1200,"h":1743},{"t":"j","w":1200,"h":1743},{"t":"j","w":1200,"h":1743},{"t":"j","w":1200,"h":1743},{"t":"j","w":1200,"h":1743},{"t":"j","w":1200,"h":1743},{"t":"j","w":1200,"h":1743},{"t":"j","w":1200,"h":1743},{"t":"j","w":1200,"h":1743},{"t":"j","w":1200,"h":1743},{"t":"j","w":1200,"h":1743},{"t":"j","w":1200,"h":1743},{"t":"j","w":1200,"h":1743},{"t":"j","w":1200,"h":1743},{"t":"j","w":1200,"h":1743},{"t":"j","w":1200,"h":1743},{"t":"j","w":1200,"h":1743},{"t":"j","w":1200,"h":1743},{"t":"j","w":1200,"h":1743},{"t":"j","w":1200,"h":1743},{"t":"j","w":1200,"h":1743},{"t":"j","w":1200,"h":1743},{"t":"j","w":1200,"h":1743},{"t":"j","w":1200,"h":1743},{"t":"j","w":1200,"h":1743},{"t":"j","w":1200,"h":1743},{"t":"j","w":1200,"h":1743},{"t":"j","w":1200,"h":1743},{"t":"j","w":1200,"h":1743},{"t":"j","w":1200,"h":1743},{"t":"j","w":1200,"h":1743},{"t":"j","w":1200,"h":1743},{"t":"j","w":1200,"h":1743},{"t":"j","w":1200,"h":1743},{"t":"j","w":1200,"h":1743},{"t":"j","w":1200,"h":1743},{"t":"j","w":1200,"h":1743},{"t":"j","w":1200,"h":1743},{"t":"j","w":1200,"h":1743},{"t":"j","w":1200,"h":1743},{"t":"j","w":1200,"h":1743},{"t":"j","w":1200,"h":1743},{"t":"j","w":1200,"h":1743},{"t":"j","w":1200,"h":1743},{"t":"j","w":1200,"h":1743},{"t":"j","w":1200,"h":1743},{"t":"j","w":1200,"h":1743},{"t":"j","w":1200,"h":1743},{"t":"j","w":1200,"h":1743},{"t":"j","w":1200,"h":1743},{"t":"j","w":1200,"h":1743},{"t":"j","w":1200,"h":1743},{"t":"j","w":1200,"h":1743},{"t":"j","w":1200,"h":1743},{"t":"j","w":1200,"h":1743},{"t":"j","w":1200,"h":1743},{"t":"j","w":1200,"h":1743},{"t":"j","w":1200,"h":1743},{"t":"j","w":1200,"h":1743},{"t":"j","w":1200,"h":1743},{"t":"j","w":1200,"h":1743},{"t":"j","w":1200,"h":1743},{"t":"j","w":1200,"h":1743},{"t":"j","w":1200,"h":1743},{"t":"j","w":1200,"h":1743},{"t":"j","w":1200,"h":1743},{"t":"j","w":1200,"h":1743},{"t":"j","w":1200,"h":1743},{"t":"j","w":1200,"h":1743},{"t":"j","w":1200,"h":1743},{"t":"j","w":1200,"h":1743},{"t":"j","w":1200,"h":1743},{"t":"j","w":1200,"h":1743},{"t":"j","w":1200,"h":1743},{"t":"j","w":1200,"h":1743},{"t":"j","w":1200,"h":1743},{"t":"j","w":1200,"h":1743},{"t":"j","w":1200,"h":1743},{"t":"j","w":1200,"h":1743},{"t":"j","w":1200,"h":1743},{"t":"j","w":1200,"h":1743},{"t":"j","w":1200,"h":1743},{"t":"j","w":1200,"h":1743},{"t":"j","w":1200,"h":1743},{"t":"j","w":1200,"h":1743},{"t":"j","w":1200,"h":1743},{"t":"j","w":1200,"h":1743},{"t":"j","w":1200,"h":1743},{"t":"j","w":1200,"h":1743},{"t":"j","w":1200,"h":1743},{"t":"j","w":1200,"h":1779},{"t":"j","w":1200,"h":1743},{"t":"j","w":1200,"h":1743},{"t":"j","w":1200,"h":1743},{"t":"j","w":1200,"h":1743},{"t":"j","w":1200,"h":1743},{"t":"j","w":1200,"h":1743},{"t":"j","w":1200,"h":1743},{"t":"j","w":1200,"h":1743},{"t":"j","w":1200,"h":1743},{"t":"j","w":1200,"h":1743},{"t":"j","w":1200,"h":1743},{"t":"j","w":1200,"h":1743},{"t":"j","w":1200,"h":1743},{"t":"j","w":1200,"h":1743},{"t":"j","w":1200,"h":1743},{"t":"j","w":1200,"h":1743},{"t":"j","w":1200,"h":1743},{"t":"j","w":1200,"h":1743},{"t":"j","w":1200,"h":1743},{"t":"j","w":1200,"h":1743},{"t":"j","w":1200,"h":1743},{"t":"j","w":1200,"h":1743},{"t":"j","w":1200,"h":1743},{"t":"j","w":1200,"h":1743},{"t":"j","w":1200,"h":1743},{"t":"j","w":1200,"h":1743},{"t":"j","w":1200,"h":1743},{"t":"j","w":1200,"h":1743},{"t":"j","w":1200,"h":1743},{"t":"j","w":1200,"h":1743},{"t":"j","w":1200,"h":1743},{"t":"j","w":1200,"h":1743},{"t":"j","w":1200,"h":1743},{"t":"j","w":1200,"h":1743},{"t":"j","w":1200,"h":1743},{"t":"j","w":1200,"h":1743},{"t":"j","w":1200,"h":1743},{"t":"j","w":1200,"h":942},{"t":"j","w":1200,"h":1743},{"t":"j","w":1200,"h":1743},{"t":"j","w":1200,"h":1743},{"t":"j","w":1200,"h":1743},{"t":"j","w":1200,"h":1743},{"t":"j","w":1200,"h":1743},{"t":"j","w":1200,"h":1743},{"t":"j","w":1200,"h":1743},{"t":"j","w":1200,"h":1743},{"t":"j","w":1200,"h":1743},{"t":"j","w":1200,"h":1743},{"t":"j","w":1200,"h":1743},{"t":"j","w":1200,"h":1743},{"t":"j","w":1200,"h":1743},{"t":"j","w":1200,"h":1743},{"t":"j","w":1200,"h":1743},{"t":"j","w":1200,"h":1743},{"t":"j","w":1200,"h":1743},{"t":"j","w":1200,"h":1743},{"t":"j","w":1200,"h":1743},{"t":"j","w":1200,"h":1743},{"t":"j","w":1200,"h":1743},{"t":"j","w":1200,"h":1743},{"t":"j","w":1200,"h":1743},{"t":"j","w":1200,"h":1743},{"t":"j","w":1200,"h":1743},{"t":"j","w":1200,"h":1743},{"t":"j","w":1200,"h":1743},{"t":"j","w":1200,"h":1743},{"t":"j","w":1200,"h":1743},{"t":"j","w":1200,"h":1743},{"t":"j","w":1200,"h":1743},{"t":"j","w":1200,"h":1743},{"t":"j","w":1200,"h":1743},{"t":"j","w":1200,"h":1743},{"t":"j","w":1200,"h":1743},{"t":"j","w":1200,"h":1743},{"t":"j","w":1200,"h":1743},{"t":"j","w":1200,"h":1743},{"t":"j","w":1200,"h":1743},{"t":"j","w":1200,"h":1743},{"t":"j","w":1200,"h":1743},{"t":"j","w":1200,"h":1743},{"t":"j","w":1200,"h":1743},{"t":"j","w":1200,"h":1743},{"t":"j","w":1200,"h":1743},{"t":"j","w":1200,"h":1743},{"t":"j","w":1200,"h":1743},{"t":"j","w":1200,"h":1743},{"t":"j","w":1200,"h":1743},{"t":"j","w":1200,"h":1743},{"t":"j","w":1200,"h":1743},{"t":"j","w":1200,"h":1743},{"t":"j","w":1200,"h":1743},{"t":"j","w":1200,"h":1743},{"t":"j","w":1200,"h":1743},{"t":"j","w":1200,"h":1743},{"t":"j","w":1200,"h":1743},{"t":"j","w":1200,"h":1743},{"t":"j","w":1200,"h":1743},{"t":"j","w":1200,"h":1743},{"t":"j","w":1200,"h":1743},{"t":"j","w":1200,"h":1743},{"t":"j","w":1200,"h":1743},{"t":"j","w":1200,"h":1743},{"t":"j","w":1200,"h":1743},{"t":"j","w":1200,"h":1743},{"t":"j","w":1200,"h":1743},{"t":"j","w":1200,"h":1743},{"t":"j","w":1200,"h":1743},{"t":"j","w":1200,"h":1743},{"t":"j","w":1200,"h":1743},{"t":"j","w":1200,"h":1743},{"t":"j","w":1200,"h":1743},{"t":"j","w":1200,"h":1743},{"t":"j","w":1200,"h":1743},{"t":"j","w":1200,"h":1743},{"t":"j","w":1200,"h":1743},{"t":"j","w":1200,"h":1743},{"t":"j","w":1200,"h":1743},{"t":"j","w":1200,"h":1743},{"t":"j","w":1200,"h":1743},{"t":"p","w":1200,"h":800},{"t":"p","w":1100,"h":516}],"cover":{"t":"j","w":350,"h":157},"thumbnail":{"t":"j","w":250,"h":112}},"scanlator":"","upload_date":1446423159,"tags":[{"id":7752,"type":"tag","name":"schoolboy uniform","url":"/tag/schoolboy-uniform/","count":12311},{"id":32341,"type":"tag","name":"shotacon","url":"/tag/shotacon/","count":39737},{"id":1067,"type":"tag","name":"inseki","url":"/tag/inseki/","count":2892},{"id":27473,"type":"tag","name":"mosaic censorship","url":"/tag/mosaic-censorship/","count":23707},{"id":23237,"type":"tag","name":"tankoubon","url":"/tag/tankoubon/","count":25051},{"id":19440,"type":"tag","name":"lolicon","url":"/tag/lolicon/","count":69490},{"id":13720,"type":"tag","name":"nakadashi","url":"/tag/nakadashi/","count":42357},{"id":29565,"type":"tag","name":"school swimsuit","url":"/tag/school-swimsuit/","count":3954},{"id":10314,"type":"tag","name":"schoolgirl uniform","url":"/tag/schoolgirl-uniform/","count":56168},{"id":24201,"type":"tag","name":"stockings","url":"/tag/stockings/","count":64784},{"id":31319,"type":"tag","name":"yandere","url":"/tag/yandere/","count":1195},{"id":29963,"type":"language","name":"chinese","url":"/language/chinese/","count":44293},{"id":17249,"type":"language","name":"translated","url":"/language/translated/","count":109734},{"id":20013,"type":"artist","name":"komiya yuuta","url":"/artist/komiya-yuuta/","count":65},{"id":33173,"type":"category","name":"manga","url":"/category/manga/","count":77142},{"id":28031,"type":"tag","name":"sister","url":"/tag/sister/","count":14555},{"id":20525,"type":"tag","name":"defloration","url":"/tag/defloration/","count":23209},{"id":22942,"type":"tag","name":"incest","url":"/tag/incest/","count":28107}],"num_pages":233,"num_favorites":329},{"id":52595,"media_id":"295488","title":{"english":"[Komiya Yuuta] Love Sickness (Manga Bangaichi 2004-11)","japanese":"[\u5c0f\u5bae\u88d5\u592a] \u604b\u60a3\u3044 (\u6f2b\u753b\u3070\u3093\u304c\u3044\u3061 2004-11)","pretty":"Love Sickness"},"images":{"pages":[{"t":"j","w":819,"h":1200},{"t":"j","w":823,"h":1200},{"t":"j","w":818,"h":1200},{"t":"j","w":828,"h":1200},{"t":"j","w":819,"h":1200},{"t":"j","w":825,"h":1200},{"t":"j","w":818,"h":1200},{"t":"j","w":812,"h":1200},{"t":"j","w":815,"h":1200},{"t":"j","w":828,"h":1200},{"t":"j","w":828,"h":1200},{"t":"j","w":811,"h":1200},{"t":"j","w":811,"h":1200},{"t":"j","w":814,"h":1200},{"t":"j","w":818,"h":1200},{"t":"j","w":808,"h":1200}],"cover":{"t":"j","w":350,"h":513},"thumbnail":{"t":"j","w":250,"h":366}},"scanlator":"","upload_date":1403991949,"tags":[{"id":20013,"type":"artist","name":"komiya yuuta","url":"/artist/komiya-yuuta/","count":65},{"id":6346,"type":"language","name":"japanese","url":"/language/japanese/","count":191613},{"id":33173,"type":"category","name":"manga","url":"/category/manga/","count":77142},{"id":10314,"type":"tag","name":"schoolgirl uniform","url":"/tag/schoolgirl-uniform/","count":56168}],"num_pages":16,"num_favorites":19}]}